[
    {
        "_id": "601e476d12ceba42e05b0108",
        "title": "Official 1 Q2",
        "TPO": 1,
        "questionNumber": 2,
        "tag": "\u6559\u80b2\u5de5\u4f5c",
        "questionType": "\u4e8c\u9009\u4e00",
        "questionType2": "Q2 \u8bdd\u9898\u5206\u7c7b",
        "userCount": 0,
        "tagCount": 1,
        "recordCount": 0
    },
    {
        "_id": "601e477312ceba42e05b0109",
        "title": "Official 1 Q3",
        "TPO": 1,
        "questionNumber": 3,
        "tag": "\u540e\u52e4\u670d\u52a1",
        "questionType": "\u7efc\u5408",
        "questionType2": "Q3 \u6821\u56ed\u573a\u666f",
        "userCount": 0,
        "tagCount": 9,
        "recordCount": 0
    },
    {
        "_id": "601e477912ceba42e05b011a",
        "title": "Official 1 Q4",
        "TPO": 1,
        "questionNumber": 4,
        "tag": "\u5546\u4e1a",
        "questionType": "\u7efc\u5408",
        "questionType2": "Q4&Q6 \u5b66\u672f\u7c7b\u8bb2\u5ea7",
        "userCount": 0,
        "tagCount": 18,
        "recordCount": 0
    },
    {
        "_id": "601e477f12ceba42e05b012f",
        "title": "Official 1 Q6",
        "TPO": 1,
        "questionNumber": 6,
        "tag": "\u5fc3\u7406",
        "questionType": "\u7efc\u5408",
        "questionType2": "Q4&Q6 \u5b66\u672f\u7c7b\u8bb2\u5ea7",
        "userCount": 0,
        "tagCount": 10,
        "recordCount": 0
    },
    {
        "_id": "601e478b12ceba42e05b0146",
        "title": "Official 2 Q2",
        "TPO": 2,
        "questionNumber": 2,
        "tag": "\u6559\u80b2\u5de5\u4f5c",
        "questionType": "\u4e8c\u9009\u4e00",
        "questionType2": "Q2 \u8bdd\u9898\u5206\u7c7b",
        "userCount": 0,
        "tagCount": 0,
        "recordCount": 0
    },
    {
        "_id": "601e479012ceba42e05b0147",
        "title": "Official 2 Q3",
        "TPO": 2,
        "questionNumber": 3,
        "tag": "\u540e\u52e4\u670d\u52a1",
        "questionType": "\u7efc\u5408",
        "questionType2": "Q3 \u6821\u56ed\u573a\u666f",
        "userCount": 0,
        "tagCount": 10,
        "recordCount": 0
    },
    {
        "_id": "601e479512ceba42e05b015a",
        "title": "Official 2 Q4",
        "TPO": 2,
        "questionNumber": 4,
        "tag": "\u793e\u4f1a\u5b66",
        "questionType": "\u7efc\u5408",
        "questionType2": "Q4&Q6 \u5b66\u672f\u7c7b\u8bb2\u5ea7",
        "userCount": 0,
        "tagCount": 11,
        "recordCount": 0
    },
    {
        "_id": "601e479812ceba42e05b0167",
        "title": "Official 2 Q6",
        "TPO": 2,
        "questionNumber": 6,
        "tag": "\u7ecf\u6d4e",
        "questionType": "\u7efc\u5408",
        "questionType2": "Q4&Q6 \u5b66\u672f\u7c7b\u8bb2\u5ea7",
        "userCount": 0,
        "tagCount": 8,
        "recordCount": 0
    },
    {
        "_id": "601e479b12ceba42e05b017d",
        "title": "Official 3 Q2",
        "TPO": 3,
        "questionNumber": 2,
        "tag": "\u6559\u80b2\u5de5\u4f5c",
        "questionType": "\u4e8c\u9009\u4e00",
        "questionType2": "Q2 \u8bdd\u9898\u5206\u7c7b",
        "userCount": 0,
        "tagCount": 0,
        "recordCount": 0
    },
    {
        "_id": "601e479f12ceba42e05b017e",
        "title": "Official 3 Q3",
        "TPO": 3,
        "questionNumber": 3,
        "tag": "\u540e\u52e4\u670d\u52a1",
        "questionType": "\u7efc\u5408",
        "questionType2": "Q3 \u6821\u56ed\u573a\u666f",
        "userCount": 0,
        "tagCount": 11,
        "recordCount": 0
    },
    {
        "_id": "601e47a312ceba42e05b018f",
        "title": "Official 3 Q4",
        "TPO": 3,
        "questionNumber": 4,
        "tag": "\u793e\u4f1a\u5b66",
        "questionType": "\u7efc\u5408",
        "questionType2": "Q4&Q6 \u5b66\u672f\u7c7b\u8bb2\u5ea7",
        "userCount": 0,
        "tagCount": 9,
        "recordCount": 0
    },
    {
        "_id": "601e47a712ceba42e05b01a3",
        "title": "Official 3 Q6",
        "TPO": 3,
        "questionNumber": 6,
        "tag": "\u5fc3\u7406",
        "questionType": "\u7efc\u5408",
        "questionType2": "Q4&Q6 \u5b66\u672f\u7c7b\u8bb2\u5ea7",
        "userCount": 0,
        "tagCount": 11,
        "recordCount": 0
    },
    {
        "_id": "601e47ab12ceba42e05b01b9",
        "title": "Official 4 Q2",
        "TPO": 4,
        "questionNumber": 2,
        "tag": "\u6559\u80b2\u5de5\u4f5c",
        "questionType": "\u4e8c\u9009\u4e00",
        "questionType2": "Q2 \u8bdd\u9898\u5206\u7c7b",
        "userCount": 0,
        "tagCount": 0,
        "recordCount": 0
    },
    {
        "_id": "601e47af12ceba42e05b01ba",
        "title": "Official 4 Q3",
        "TPO": 4,
        "questionNumber": 3,
        "tag": "\u8bfe\u7a0b\u5b89\u6392",
        "questionType": "\u7efc\u5408",
        "questionType2": "Q3 \u6821\u56ed\u573a\u666f",
        "userCount": 0,
        "tagCount": 11,
        "recordCount": 0
    },
    {
        "_id": "601e47b312ceba42e05b01cc",
        "title": "Official 4 Q4",
        "TPO": 4,
        "questionNumber": 4,
        "tag": "\u5fc3\u7406",
        "questionType": "\u7efc\u5408",
        "questionType2": "Q4&Q6 \u5b66\u672f\u7c7b\u8bb2\u5ea7",
        "userCount": 0,
        "tagCount": 14,
        "recordCount": 0
    },
    {
        "_id": "601e47b612ceba42e05b01de",
        "title": "Official 4 Q6",
        "TPO": 4,
        "questionNumber": 6,
        "tag": "\u827a\u672f",
        "questionType": "\u7efc\u5408",
        "questionType2": "Q4&Q6 \u5b66\u672f\u7c7b\u8bb2\u5ea7",
        "userCount": 0,
        "tagCount": 10,
        "recordCount": 0
    },
    {
        "_id": "601e47bc12ceba42e05b01f3",
        "title": "Official 5 Q2",
        "TPO": 5,
        "questionNumber": 2,
        "tag": "\u6559\u80b2\u5de5\u4f5c",
        "questionType": "Agree or Disagree",
        "questionType2": "Q2 \u8bdd\u9898\u5206\u7c7b",
        "userCount": 0,
        "tagCount": 0,
        "recordCount": 0
    },
    {
        "_id": "601e47be12ceba42e05b01f4",
        "title": "Official 5 Q3",
        "TPO": 5,
        "questionNumber": 3,
        "tag": "\u6821\u56ed\u573a\u666f",
        "questionType": "\u7efc\u5408",
        "questionType2": "Q3 \u6821\u56ed\u573a\u666f",
        "userCount": 0,
        "tagCount": 16,
        "recordCount": 0
    },
    {
        "_id": "601e47c212ceba42e05b020a",
        "title": "Official 5 Q4",
        "TPO": 5,
        "questionNumber": 4,
        "tag": "\u5546\u4e1a",
        "questionType": "\u7efc\u5408",
        "questionType2": "Q4&Q6 \u5b66\u672f\u7c7b\u8bb2\u5ea7",
        "userCount": 0,
        "tagCount": 11,
        "recordCount": 0
    },
    {
        "_id": "603388b38f7c547959409dcb",
        "title": "Official 5 Q6",
        "TPO": 5,
        "questionNumber": 6,
        "tag": "\u5fc3\u7406",
        "questionType": "\u7efc\u5408",
        "questionType2": "Q4&Q6 \u5b66\u672f\u7c7b\u8bb2\u5ea7",
        "userCount": 0,
        "tagCount": 15,
        "recordCount": 0
    },
    {
        "_id": "601e47cb12ceba42e05b022a",
        "title": "Official 6 Q2",
        "TPO": 6,
        "questionNumber": 2,
        "tag": "\u6559\u80b2\u5de5\u4f5c",
        "questionType": "\u4e8c\u9009\u4e00",
        "questionType2": "Q2 \u8bdd\u9898\u5206\u7c7b",
        "userCount": 0,
        "tagCount": 0,
        "recordCount": 0
    },
    {
        "_id": "601e47cd12ceba42e05b022b",
        "title": "Official 6 Q3",
        "TPO": 6,
        "questionNumber": 3,
        "tag": "\u8bfe\u7a0b\u5b89\u6392",
        "questionType": "\u7efc\u5408",
        "questionType2": "Q3 \u6821\u56ed\u573a\u666f",
        "userCount": 0,
        "tagCount": 17,
        "recordCount": 0
    },
    {
        "_id": "601e47d012ceba42e05b023c",
        "title": "Official 6 Q4",
        "TPO": 6,
        "questionNumber": 4,
        "tag": "\u5fc3\u7406",
        "questionType": "\u7efc\u5408",
        "questionType2": "Q4&Q6 \u5b66\u672f\u7c7b\u8bb2\u5ea7",
        "userCount": 0,
        "tagCount": 14,
        "recordCount": 0
    },
    {
        "_id": "6034d4fcc28a9e1393c96051",
        "title": "Official 6 Q6",
        "TPO": 6,
        "questionNumber": 6,
        "tag": "\u6559\u80b2",
        "questionType": "\u7efc\u5408",
        "questionType2": "Q4&Q6 \u5b66\u672f\u7c7b\u8bb2\u5ea7",
        "userCount": 0,
        "tagCount": 16,
        "recordCount": 0
    },
    {
        "_id": "601e47d712ceba42e05b0253",
        "title": "Official 7 Q2",
        "TPO": 7,
        "questionNumber": 2,
        "tag": "\u6559\u80b2\u5de5\u4f5c",
        "questionType": "Agree or Disagree",
        "questionType2": "Q2 \u8bdd\u9898\u5206\u7c7b",
        "userCount": 0,
        "tagCount": 0,
        "recordCount": 0
    },
    {
        "_id": "601e47da12ceba42e05b0254",
        "title": "Official 7 Q3",
        "TPO": 7,
        "questionNumber": 3,
        "tag": "\u8bfe\u7a0b\u5b89\u6392",
        "questionType": "\u7efc\u5408",
        "questionType2": "Q3 \u6821\u56ed\u573a\u666f",
        "userCount": 0,
        "tagCount": 12,
        "recordCount": 0
    },
    {
        "_id": "601e47dd12ceba42e05b026c",
        "title": "Official 7 Q4",
        "TPO": 7,
        "questionNumber": 4,
        "tag": "\u5fc3\u7406",
        "questionType": "\u7efc\u5408",
        "questionType2": "Q4&Q6 \u5b66\u672f\u7c7b\u8bb2\u5ea7",
        "userCount": 0,
        "tagCount": 15,
        "recordCount": 0
    },
    {
        "_id": "601e47e012ceba42e05b027a",
        "title": "Official 7 Q6",
        "TPO": 7,
        "questionNumber": 6,
        "tag": "\u5546\u4e1a",
        "questionType": "\u7efc\u5408",
        "questionType2": "Q4&Q6 \u5b66\u672f\u7c7b\u8bb2\u5ea7",
        "userCount": 0,
        "tagCount": 12,
        "recordCount": 0
    },
    {
        "_id": "601e47e312ceba42e05b0291",
        "title": "Official 8 Q2",
        "TPO": 8,
        "questionNumber": 2,
        "tag": "\u751f\u6d3b\u65b9\u5f0f",
        "questionType": "\u4e8c\u9009\u4e00",
        "questionType2": "Q2 \u8bdd\u9898\u5206\u7c7b",
        "userCount": 0,
        "tagCount": 0,
        "recordCount": 0
    },
    {
        "_id": "601e47e612ceba42e05b0292",
        "title": "Official 8 Q3",
        "TPO": 8,
        "questionNumber": 3,
        "tag": "\u540e\u52e4\u670d\u52a1",
        "questionType": "\u7efc\u5408",
        "questionType2": "Q3 \u6821\u56ed\u573a\u666f",
        "userCount": 0,
        "tagCount": 11,
        "recordCount": 0
    },
    {
        "_id": "601e47ef12ceba42e05b02a2",
        "title": "Official 8 Q4",
        "TPO": 8,
        "questionNumber": 4,
        "tag": "\u751f\u7269",
        "questionType": "\u7efc\u5408",
        "questionType2": "Q4&Q6 \u5b66\u672f\u7c7b\u8bb2\u5ea7",
        "userCount": 0,
        "tagCount": 21,
        "recordCount": 0
    },
    {
        "_id": "601e47f212ceba42e05b02af",
        "title": "Official 8 Q6",
        "TPO": 8,
        "questionNumber": 6,
        "tag": "\u5546\u4e1a",
        "questionType": "\u7efc\u5408",
        "questionType2": "Q4&Q6 \u5b66\u672f\u7c7b\u8bb2\u5ea7",
        "userCount": 0,
        "tagCount": 12,
        "recordCount": 0
    },
    {
        "_id": "601e47f612ceba42e05b02c3",
        "title": "Official 9 Q2",
        "TPO": 9,
        "questionNumber": 2,
        "tag": "\u751f\u6d3b\u65b9\u5f0f",
        "questionType": "\u4e8c\u9009\u4e00",
        "questionType2": "Q2 \u8bdd\u9898\u5206\u7c7b",
        "userCount": 0,
        "tagCount": 0,
        "recordCount": 0
    },
    {
        "_id": "601e47fa12ceba42e05b02c4",
        "title": "Official 9 Q3",
        "TPO": 9,
        "questionNumber": 3,
        "tag": "\u5de5\u4f5c\u5b9e\u4e60",
        "questionType": "\u7efc\u5408",
        "questionType2": "Q3 \u6821\u56ed\u573a\u666f",
        "userCount": 0,
        "tagCount": 12,
        "recordCount": 0
    },
    {
        "_id": "601e47fd12ceba42e05b02d1",
        "title": "Official 9 Q4",
        "TPO": 9,
        "questionNumber": 4,
        "tag": "\u827a\u672f",
        "questionType": "\u7efc\u5408",
        "questionType2": "Q4&Q6 \u5b66\u672f\u7c7b\u8bb2\u5ea7",
        "userCount": 0,
        "tagCount": 17,
        "recordCount": 0
    },
    {
        "_id": "601e480112ceba42e05b02e0",
        "title": "Official 9 Q6",
        "TPO": 9,
        "questionNumber": 6,
        "tag": "\u751f\u7269",
        "questionType": "\u7efc\u5408",
        "questionType2": "Q4&Q6 \u5b66\u672f\u7c7b\u8bb2\u5ea7",
        "userCount": 0,
        "tagCount": 14,
        "recordCount": 0
    },
    {
        "_id": "600e51519db0f2049a96691e",
        "title": "Official 10 Q2",
        "TPO": 10,
        "questionNumber": 2,
        "tag": "\u6559\u80b2\u5de5\u4f5c",
        "questionType": "Agree or Disagree",
        "questionType2": "Q2 \u8bdd\u9898\u5206\u7c7b",
        "userCount": 0,
        "tagCount": 0,
        "recordCount": 0
    },
    {
        "_id": "600e524e9db0f2049a966925",
        "title": "Official 10 Q3",
        "TPO": 10,
        "questionNumber": 3,
        "tag": "\u6821\u56ed\u5efa\u8bbe",
        "questionType": "\u7efc\u5408",
        "questionType2": "Q3 \u6821\u56ed\u573a\u666f",
        "userCount": 0,
        "tagCount": 12,
        "recordCount": 0
    },
    {
        "_id": "600e54be9db0f2049a967b1b",
        "title": "Official 10 Q4",
        "TPO": 10,
        "questionNumber": 4,
        "tag": "\u5546\u4e1a",
        "questionType": "\u7efc\u5408",
        "questionType2": "Q4&Q6 \u5b66\u672f\u7c7b\u8bb2\u5ea7",
        "userCount": 0,
        "tagCount": 11,
        "recordCount": 0
    },
    {
        "_id": "600e55e49db0f2049a967b34",
        "title": "Official 10 Q6",
        "TPO": 10,
        "questionNumber": 6,
        "tag": "\u5fc3\u7406",
        "questionType": "\u7efc\u5408",
        "questionType2": "Q4&Q6 \u5b66\u672f\u7c7b\u8bb2\u5ea7",
        "userCount": 0,
        "tagCount": 10,
        "recordCount": 0
    },
    {
        "_id": "609cd01c733fc20c352c395d",
        "title": "Official 11 Q2",
        "TPO": 11,
        "questionNumber": 2,
        "tag": "\u793e\u4f1a\u8bdd\u9898",
        "questionType": "\u4e8c\u9009\u4e00",
        "questionType2": "Q2 \u8bdd\u9898\u5206\u7c7b",
        "userCount": 0,
        "tagCount": 0,
        "recordCount": 0
    },
    {
        "_id": "609de05a095e917278ad0deb",
        "title": "Official 11 Q3",
        "TPO": 11,
        "questionNumber": 3,
        "tag": "\u540e\u52e4\u670d\u52a1",
        "questionType": "\u7efc\u5408",
        "questionType2": "Q3 \u6821\u56ed\u573a\u666f",
        "userCount": 0,
        "tagCount": 9,
        "recordCount": 0
    },
    {
        "_id": "609de6d9095e917278ad12ca",
        "title": "Official 11 Q4",
        "TPO": 11,
        "questionNumber": 4,
        "tag": "\u827a\u672f",
        "questionType": "\u7efc\u5408",
        "questionType2": "Q4&Q6 \u5b66\u672f\u7c7b\u8bb2\u5ea7",
        "userCount": 0,
        "tagCount": 13,
        "recordCount": 0
    },
    {
        "_id": "609de85b095e917278ad12ee",
        "title": "Official 11 Q6",
        "TPO": 11,
        "questionNumber": 6,
        "tag": "\u827a\u672f",
        "questionType": "\u7efc\u5408",
        "questionType2": "Q4&Q6 \u5b66\u672f\u7c7b\u8bb2\u5ea7",
        "userCount": 0,
        "tagCount": 11,
        "recordCount": 0
    },
    {
        "_id": "609dea3e095e917278ad132d",
        "title": "Official 12 Q2",
        "TPO": 12,
        "questionNumber": 2,
        "tag": "\u6559\u80b2\u5de5\u4f5c",
        "questionType": "\u4e8c\u9009\u4e00",
        "questionType2": "Q2 \u8bdd\u9898\u5206\u7c7b",
        "userCount": 0,
        "tagCount": 0,
        "recordCount": 0
    },
    {
        "_id": "609dedd6095e917278ad13cd",
        "title": "Official 12 Q3",
        "TPO": 12,
        "questionNumber": 3,
        "tag": "\u6821\u56ed\u573a\u666f",
        "questionType": "\u7efc\u5408",
        "questionType2": "Q3 \u6821\u56ed\u573a\u666f",
        "userCount": 0,
        "tagCount": 11,
        "recordCount": 0
    },
    {
        "_id": "609df00b095e917278ad1f67",
        "title": "Official 12 Q4",
        "TPO": 12,
        "questionNumber": 4,
        "tag": "\u5b66\u672f\u7c7b\u8bb2\u5ea7",
        "questionType": "\u7efc\u5408",
        "questionType2": "Q4&Q6 \u5b66\u672f\u7c7b\u8bb2\u5ea7",
        "userCount": 0,
        "tagCount": 12,
        "recordCount": 0
    },
    {
        "_id": "609e0d9fc56edb2eb9e15147",
        "title": "Official 12 Q6",
        "TPO": 12,
        "questionNumber": 6,
        "tag": "\u7ecf\u6d4e",
        "questionType": "\u7efc\u5408",
        "questionType2": "Q4&Q6 \u5b66\u672f\u7c7b\u8bb2\u5ea7",
        "userCount": 0,
        "tagCount": 13,
        "recordCount": 0
    },
    {
        "_id": "609e0e8dc56edb2eb9e157a3",
        "title": "Official 13 Q2",
        "TPO": 13,
        "questionNumber": 2,
        "tag": "\u6559\u80b2\u5de5\u4f5c",
        "questionType": "\u4e8c\u9009\u4e00",
        "questionType2": "Q2 \u8bdd\u9898\u5206\u7c7b",
        "userCount": 0,
        "tagCount": 0,
        "recordCount": 0
    },
    {
        "_id": "609e110bc56edb2eb9e1648b",
        "title": "Official 13 Q3",
        "TPO": 13,
        "questionNumber": 3,
        "tag": "\u6821\u56ed\u573a\u666f",
        "questionType": "\u7efc\u5408",
        "questionType2": "Q3 \u6821\u56ed\u573a\u666f",
        "userCount": 0,
        "tagCount": 0,
        "recordCount": 0
    },
    {
        "_id": "609e1193c56edb2eb9e166c7",
        "title": "Official 13 Q4",
        "TPO": 13,
        "questionNumber": 4,
        "tag": "\u5fc3\u7406",
        "questionType": "\u7efc\u5408",
        "questionType2": "Q4&Q6 \u5b66\u672f\u7c7b\u8bb2\u5ea7",
        "userCount": 0,
        "tagCount": 0,
        "recordCount": 0
    },
    {
        "_id": "609e126bc56edb2eb9e1670f",
        "title": "Official 13 Q6",
        "TPO": 13,
        "questionNumber": 6,
        "tag": "\u751f\u7269",
        "questionType": "\u7efc\u5408",
        "questionType2": "Q4&Q6 \u5b66\u672f\u7c7b\u8bb2\u5ea7",
        "userCount": 0,
        "tagCount": 0,
        "recordCount": 0
    },
    {
        "_id": "609e15b3c56edb2eb9e16a87",
        "title": "Official 14 Q2",
        "TPO": 14,
        "questionNumber": 2,
        "tag": "\u751f\u6d3b\u65b9\u5f0f",
        "questionType": "Agree or Disagree",
        "questionType2": "Q2 \u8bdd\u9898\u5206\u7c7b",
        "userCount": 0,
        "tagCount": 0,
        "recordCount": 0
    },
    {
        "_id": "609e1733c56edb2eb9e16bd5",
        "title": "Official 14 Q3",
        "TPO": 14,
        "questionNumber": 3,
        "tag": "\u540e\u52e4\u670d\u52a1",
        "questionType": "\u7efc\u5408",
        "questionType2": "Q3 \u6821\u56ed\u573a\u666f",
        "userCount": 0,
        "tagCount": 10,
        "recordCount": 0
    },
    {
        "_id": "609e189cc56edb2eb9e16bf5",
        "title": "Official 14 Q4",
        "TPO": 14,
        "questionNumber": 4,
        "tag": "\u5fc3\u7406",
        "questionType": "\u7efc\u5408",
        "questionType2": "Q4&Q6 \u5b66\u672f\u7c7b\u8bb2\u5ea7",
        "userCount": 0,
        "tagCount": 15,
        "recordCount": 0
    },
    {
        "_id": "609e199cc56edb2eb9e16cca",
        "title": "Official 14 Q6",
        "TPO": 14,
        "questionNumber": 6,
        "tag": "\u751f\u7269",
        "questionType": "\u7efc\u5408",
        "questionType2": "Q4&Q6 \u5b66\u672f\u7c7b\u8bb2\u5ea7",
        "userCount": 0,
        "tagCount": 13,
        "recordCount": 0
    },
    {
        "_id": "609e1c48c56edb2eb9e170b9",
        "title": "Official 15 Q2",
        "TPO": 15,
        "questionNumber": 2,
        "tag": "\u751f\u6d3b\u65b9\u5f0f",
        "questionType": "Agree or Disagree",
        "questionType2": "Q2 \u8bdd\u9898\u5206\u7c7b",
        "userCount": 0,
        "tagCount": 0,
        "recordCount": 0
    },
    {
        "_id": "609e1c8dc56edb2eb9e17144",
        "title": "Official 15 Q3",
        "TPO": 15,
        "questionNumber": 3,
        "tag": "\u57fa\u7840\u5efa\u8bbe",
        "questionType": "\u7efc\u5408",
        "questionType2": "Q3 \u6821\u56ed\u573a\u666f",
        "userCount": 0,
        "tagCount": 0,
        "recordCount": 0
    },
    {
        "_id": "609e1dbcc56edb2eb9e17361",
        "title": "Official 15 Q4",
        "TPO": 15,
        "questionNumber": 4,
        "tag": "\u5fc3\u7406",
        "questionType": "\u7efc\u5408",
        "questionType2": "Q4&Q6 \u5b66\u672f\u7c7b\u8bb2\u5ea7",
        "userCount": 0,
        "tagCount": 0,
        "recordCount": 0
    },
    {
        "_id": "609e1ecdc56edb2eb9e17460",
        "title": "Official 15 Q6",
        "TPO": 15,
        "questionNumber": 6,
        "tag": "\u751f\u7269",
        "questionType": "\u7efc\u5408",
        "questionType2": "Q4&Q6 \u5b66\u672f\u7c7b\u8bb2\u5ea7",
        "userCount": 0,
        "tagCount": 0,
        "recordCount": 0
    },
    {
        "_id": "609e20e3c56edb2eb9e1757b",
        "title": "Official 16 Q2",
        "TPO": 16,
        "questionNumber": 2,
        "tag": "\u751f\u6d3b\u65b9\u5f0f",
        "questionType": "\u4e8c\u9009\u4e00",
        "questionType2": "Q2 \u8bdd\u9898\u5206\u7c7b",
        "userCount": 0,
        "tagCount": 0,
        "recordCount": 0
    },
    {
        "_id": "609e24a4c56edb2eb9e175ee",
        "title": "Official 16 Q3",
        "TPO": 16,
        "questionNumber": 3,
        "tag": "\u540e\u52e4\u670d\u52a1",
        "questionType": "\u7efc\u5408",
        "questionType2": "Q3 \u6821\u56ed\u573a\u666f",
        "userCount": 0,
        "tagCount": 0,
        "recordCount": 0
    },
    {
        "_id": "609e2664c56edb2eb9e17ab4",
        "title": "Official 16 Q4",
        "TPO": 16,
        "questionNumber": 4,
        "tag": "\u5fc3\u7406",
        "questionType": "\u7efc\u5408",
        "questionType2": "Q4&Q6 \u5b66\u672f\u7c7b\u8bb2\u5ea7",
        "userCount": 0,
        "tagCount": 0,
        "recordCount": 0
    },
    {
        "_id": "609e2780c56edb2eb9e17acf",
        "title": "Official 16 Q6",
        "TPO": 16,
        "questionNumber": 6,
        "tag": "\u5fc3\u7406",
        "questionType": "\u7efc\u5408",
        "questionType2": "Q4&Q6 \u5b66\u672f\u7c7b\u8bb2\u5ea7",
        "userCount": 0,
        "tagCount": 0,
        "recordCount": 0
    },
    {
        "_id": "609e28efc56edb2eb9e18043",
        "title": "Official 17 Q2",
        "TPO": 17,
        "questionNumber": 2,
        "tag": "\u6559\u80b2\u5de5\u4f5c",
        "questionType": "Agree or Disagree",
        "questionType2": "Q2 \u8bdd\u9898\u5206\u7c7b",
        "userCount": 0,
        "tagCount": 0,
        "recordCount": 0
    },
    {
        "_id": "609e2b67c56edb2eb9e189b7",
        "title": "Official 17 Q3",
        "TPO": 17,
        "questionNumber": 3,
        "tag": "\u57fa\u7840\u5efa\u8bbe",
        "questionType": "\u7efc\u5408",
        "questionType2": "Q3 \u6821\u56ed\u573a\u666f",
        "userCount": 0,
        "tagCount": 0,
        "recordCount": 0
    },
    {
        "_id": "609e2c9ac56edb2eb9e18e08",
        "title": "Official 17 Q4",
        "TPO": 17,
        "questionNumber": 4,
        "tag": "\u751f\u7269",
        "questionType": "\u7efc\u5408",
        "questionType2": "Q4&Q6 \u5b66\u672f\u7c7b\u8bb2\u5ea7",
        "userCount": 0,
        "tagCount": 0,
        "recordCount": 0
    },
    {
        "_id": "609e2e1bc56edb2eb9e19523",
        "title": "Official 17 Q6",
        "TPO": 17,
        "questionNumber": 6,
        "tag": "\u793e\u4f1a\u5b66",
        "questionType": "\u7efc\u5408",
        "questionType2": "Q4&Q6 \u5b66\u672f\u7c7b\u8bb2\u5ea7",
        "userCount": 0,
        "tagCount": 0,
        "recordCount": 0
    },
    {
        "_id": "609e2f5bc56edb2eb9e19a4f",
        "title": "Official 18 Q2",
        "TPO": 18,
        "questionNumber": 2,
        "tag": "\u6559\u80b2\u5de5\u4f5c",
        "questionType": "\u4e8c\u9009\u4e00",
        "questionType2": "Q2 \u8bdd\u9898\u5206\u7c7b",
        "userCount": 0,
        "tagCount": 0,
        "recordCount": 0
    },
    {
        "_id": "609e3097c56edb2eb9e19fba",
        "title": "Official 18 Q3",
        "TPO": 18,
        "questionNumber": 3,
        "tag": "\u8bfe\u5916\u6d3b\u52a8",
        "questionType": "\u7efc\u5408",
        "questionType2": "Q3 \u6821\u56ed\u573a\u666f",
        "userCount": 0,
        "tagCount": 0,
        "recordCount": 0
    },
    {
        "_id": "609e3231c56edb2eb9e1a38e",
        "title": "Official 18 Q4",
        "TPO": 18,
        "questionNumber": 4,
        "tag": "\u751f\u7269",
        "questionType": "\u7efc\u5408",
        "questionType2": "Q4&Q6 \u5b66\u672f\u7c7b\u8bb2\u5ea7",
        "userCount": 0,
        "tagCount": 0,
        "recordCount": 0
    },
    {
        "_id": "609e3366c56edb2eb9e1a572",
        "title": "Official 18 Q6",
        "TPO": 18,
        "questionNumber": 6,
        "tag": "\u5546\u4e1a",
        "questionType": "\u7efc\u5408",
        "questionType2": "Q4&Q6 \u5b66\u672f\u7c7b\u8bb2\u5ea7",
        "userCount": 0,
        "tagCount": 0,
        "recordCount": 0
    },
    {
        "_id": "609e36ccc56edb2eb9e1ab76",
        "title": "Official 19 Q2",
        "TPO": 19,
        "questionNumber": 2,
        "tag": "\u751f\u6d3b\u65b9\u5f0f",
        "questionType": "\u4e8c\u9009\u4e00",
        "questionType2": "Q2 \u8bdd\u9898\u5206\u7c7b",
        "userCount": 0,
        "tagCount": 0,
        "recordCount": 0
    },
    {
        "_id": "609e3ddb9678ff61ba74bab1",
        "title": "Official 19 Q3",
        "TPO": 19,
        "questionNumber": 3,
        "tag": "\u57fa\u7840\u5efa\u8bbe",
        "questionType": "\u7efc\u5408",
        "questionType2": "Q3 \u6821\u56ed\u573a\u666f",
        "userCount": 0,
        "tagCount": 0,
        "recordCount": 0
    },
    {
        "_id": "609e40b256a2e66668f4faa2",
        "title": "Official 19 Q4",
        "TPO": 19,
        "questionNumber": 4,
        "tag": "\u5fc3\u7406",
        "questionType": "\u7efc\u5408",
        "questionType2": "Q4&Q6 \u5b66\u672f\u7c7b\u8bb2\u5ea7",
        "userCount": 0,
        "tagCount": 0,
        "recordCount": 0
    },
    {
        "_id": "609e41d556a2e66668f4fb8f",
        "title": "Official 19 Q6",
        "TPO": 19,
        "questionNumber": 6,
        "tag": "\u751f\u7269",
        "questionType": "\u7efc\u5408",
        "questionType2": "Q4&Q6 \u5b66\u672f\u7c7b\u8bb2\u5ea7",
        "userCount": 0,
        "tagCount": 0,
        "recordCount": 0
    },
    {
        "_id": "609e42762bb0bb6df68edb8c",
        "title": "Official 20 Q2",
        "TPO": 20,
        "questionNumber": 2,
        "tag": "\u751f\u6d3b\u65b9\u5f0f",
        "questionType": "\u4e8c\u9009\u4e00",
        "questionType2": "Q2 \u8bdd\u9898\u5206\u7c7b",
        "userCount": 0,
        "tagCount": 0,
        "recordCount": 0
    },
    {
        "_id": "609e43822bb0bb6df68edbe9",
        "title": "Official 20 Q3",
        "TPO": 20,
        "questionNumber": 3,
        "tag": "\u57fa\u7840\u5efa\u8bbe",
        "questionType": "\u7efc\u5408",
        "questionType2": "Q3 \u6821\u56ed\u573a\u666f",
        "userCount": 0,
        "tagCount": 18,
        "recordCount": 0
    },
    {
        "_id": "609e44dd2bb0bb6df68edc3f",
        "title": "Official 20 Q4",
        "TPO": 20,
        "questionNumber": 4,
        "tag": "\u5546\u4e1a",
        "questionType": "\u7efc\u5408",
        "questionType2": "Q4&Q6 \u5b66\u672f\u7c7b\u8bb2\u5ea7",
        "userCount": 0,
        "tagCount": 11,
        "recordCount": 0
    },
    {
        "_id": "609e45e72bb0bb6df68edc57",
        "title": "Official 20 Q6",
        "TPO": 20,
        "questionNumber": 6,
        "tag": "\u5fc3\u7406",
        "questionType": "\u7efc\u5408",
        "questionType2": "Q4&Q6 \u5b66\u672f\u7c7b\u8bb2\u5ea7",
        "userCount": 0,
        "tagCount": 12,
        "recordCount": 0
    },
    {
        "_id": "60b5e4fa9f0a7466e7dbdb25",
        "title": "Official 21 Q2",
        "TPO": 21,
        "questionNumber": 2,
        "tag": "\u4e2a\u4eba\u7ecf\u5386",
        "questionType": "Agree or Disagree",
        "questionType2": "Q2 \u8bdd\u9898\u5206\u7c7b",
        "userCount": 0,
        "tagCount": 0,
        "recordCount": 0
    },
    {
        "_id": "60b5eb55cf3b991f89402fab",
        "title": "Official 21 Q3",
        "TPO": 21,
        "questionNumber": 3,
        "tag": "\u8bfe\u5916\u6d3b\u52a8",
        "questionType": "\u7efc\u5408",
        "questionType2": "Q3 \u6821\u56ed\u573a\u666f",
        "userCount": 0,
        "tagCount": 19,
        "recordCount": 0
    },
    {
        "_id": "60b5edf6e0308a24fc3c3781",
        "title": "Official 21 Q4",
        "TPO": 21,
        "questionNumber": 4,
        "tag": "\u5fc3\u7406",
        "questionType": "\u7efc\u5408",
        "questionType2": "Q4&Q6 \u5b66\u672f\u7c7b\u8bb2\u5ea7",
        "userCount": 0,
        "tagCount": 13,
        "recordCount": 0
    },
    {
        "_id": "60b5f03a7716ce2f948a3c7b",
        "title": "Official 21 Q6",
        "TPO": 21,
        "questionNumber": 6,
        "tag": "\u5386\u53f2",
        "questionType": "\u7efc\u5408",
        "questionType2": "Q4&Q6 \u5b66\u672f\u7c7b\u8bb2\u5ea7",
        "userCount": 0,
        "tagCount": 19,
        "recordCount": 0
    },
    {
        "_id": "60b5f1fdf1ef4f3526b5ae39",
        "title": "Official 22 Q2",
        "TPO": 22,
        "questionNumber": 2,
        "tag": "\u6559\u80b2\u5de5\u4f5c",
        "questionType": "Agree or Disagree",
        "questionType2": "Q2 \u8bdd\u9898\u5206\u7c7b",
        "userCount": 0,
        "tagCount": 0,
        "recordCount": 0
    },
    {
        "_id": "60b5f374af828039e300346e",
        "title": "Official 22 Q3",
        "TPO": 22,
        "questionNumber": 3,
        "tag": "\u8bfe\u5916\u6d3b\u52a8",
        "questionType": "\u7efc\u5408",
        "questionType2": "Q3 \u6821\u56ed\u573a\u666f",
        "userCount": 0,
        "tagCount": 13,
        "recordCount": 0
    },
    {
        "_id": "60b5f549af828039e300348c",
        "title": "Official 22 Q4",
        "TPO": 22,
        "questionNumber": 4,
        "tag": "\u5fc3\u7406",
        "questionType": "\u7efc\u5408",
        "questionType2": "Q4&Q6 \u5b66\u672f\u7c7b\u8bb2\u5ea7",
        "userCount": 0,
        "tagCount": 27,
        "recordCount": 0
    },
    {
        "_id": "60b5f642af828039e30034e1",
        "title": "Official 22 Q6",
        "TPO": 22,
        "questionNumber": 6,
        "tag": "\u751f\u7269",
        "questionType": "\u7efc\u5408",
        "questionType2": "Q4&Q6 \u5b66\u672f\u7c7b\u8bb2\u5ea7",
        "userCount": 0,
        "tagCount": 26,
        "recordCount": 0
    },
    {
        "_id": "60b5f759af828039e300350e",
        "title": "Official 23 Q2",
        "TPO": 23,
        "questionNumber": 2,
        "tag": "\u751f\u6d3b\u65b9\u5f0f",
        "questionType": "\u4e8c\u9009\u4e00",
        "questionType2": "Q2 \u8bdd\u9898\u5206\u7c7b",
        "userCount": 0,
        "tagCount": 0,
        "recordCount": 0
    },
    {
        "_id": "60b5f8bbaf828039e3003544",
        "title": "Official 23 Q3",
        "TPO": 23,
        "questionNumber": 3,
        "tag": "\u8bfe\u5916\u6d3b\u52a8",
        "questionType": "\u7efc\u5408",
        "questionType2": "Q3 \u6821\u56ed\u573a\u666f",
        "userCount": 0,
        "tagCount": 16,
        "recordCount": 0
    },
    {
        "_id": "60b5fa0daf828039e3003575",
        "title": "Official 23 Q4",
        "TPO": 23,
        "questionNumber": 4,
        "tag": "\u793e\u4f1a\u5b66",
        "questionType": "\u7efc\u5408",
        "questionType2": "Q4&Q6 \u5b66\u672f\u7c7b\u8bb2\u5ea7",
        "userCount": 0,
        "tagCount": 25,
        "recordCount": 0
    },
    {
        "_id": "60b5fb03af828039e30035a5",
        "title": "Official 23 Q6",
        "TPO": 23,
        "questionNumber": 6,
        "tag": "\u751f\u7269",
        "questionType": "\u7efc\u5408",
        "questionType2": "Q4&Q6 \u5b66\u672f\u7c7b\u8bb2\u5ea7",
        "userCount": 0,
        "tagCount": 18,
        "recordCount": 0
    },
    {
        "_id": "60b5fbd1af828039e30035f0",
        "title": "Official 24 Q2",
        "TPO": 24,
        "questionNumber": 2,
        "tag": "\u6559\u80b2\u5de5\u4f5c",
        "questionType": "Agree or Disagree",
        "questionType2": "Q2 \u8bdd\u9898\u5206\u7c7b",
        "userCount": 0,
        "tagCount": 0,
        "recordCount": 0
    },
    {
        "_id": "60b5fd31af828039e30035fb",
        "title": "Official 24 Q3",
        "TPO": 24,
        "questionNumber": 3,
        "tag": "\u57fa\u7840\u5efa\u8bbe",
        "questionType": "\u7efc\u5408",
        "questionType2": "Q3 \u6821\u56ed\u573a\u666f",
        "userCount": 0,
        "tagCount": 24,
        "recordCount": 0
    },
    {
        "_id": "60b5fe9daf828039e300361c",
        "title": "Official 24 Q4",
        "TPO": 24,
        "questionNumber": 4,
        "tag": "\u73af\u5883",
        "questionType": "\u7efc\u5408",
        "questionType2": "Q4&Q6 \u5b66\u672f\u7c7b\u8bb2\u5ea7",
        "userCount": 0,
        "tagCount": 23,
        "recordCount": 0
    },
    {
        "_id": "60b5ff72af828039e300364f",
        "title": "Official 24 Q6",
        "TPO": 24,
        "questionNumber": 6,
        "tag": "\u6587\u5b66",
        "questionType": "\u7efc\u5408",
        "questionType2": "Q4&Q6 \u5b66\u672f\u7c7b\u8bb2\u5ea7",
        "userCount": 0,
        "tagCount": 14,
        "recordCount": 0
    },
    {
        "_id": "60b60039af828039e30037af",
        "title": "Official 25 Q2",
        "TPO": 25,
        "questionNumber": 2,
        "tag": "\u751f\u6d3b\u65b9\u5f0f",
        "questionType": "\u4e8c\u9009\u4e00",
        "questionType2": "Q2 \u8bdd\u9898\u5206\u7c7b",
        "userCount": 0,
        "tagCount": 0,
        "recordCount": 0
    },
    {
        "_id": "60b6011b6b799b5b1913d5d5",
        "title": "Official 25 Q3",
        "TPO": 25,
        "questionNumber": 3,
        "tag": "\u8bfe\u5916\u6d3b\u52a8",
        "questionType": "\u7efc\u5408",
        "questionType2": "Q3 \u6821\u56ed\u573a\u666f",
        "userCount": 0,
        "tagCount": 19,
        "recordCount": 0
    },
    {
        "_id": "60b601f96b799b5b1913d66b",
        "title": "Official 25 Q4",
        "TPO": 25,
        "questionNumber": 4,
        "tag": "\u793e\u4f1a\u5b66",
        "questionType": "\u7efc\u5408",
        "questionType2": "Q4&Q6 \u5b66\u672f\u7c7b\u8bb2\u5ea7",
        "userCount": 0,
        "tagCount": 18,
        "recordCount": 0
    },
    {
        "_id": "60b602b96b799b5b1913d68c",
        "title": "Official 25 Q6",
        "TPO": 25,
        "questionNumber": 6,
        "tag": "\u5730\u8d28",
        "questionType": "\u7efc\u5408",
        "questionType2": "Q4&Q6 \u5b66\u672f\u7c7b\u8bb2\u5ea7",
        "userCount": 0,
        "tagCount": 12,
        "recordCount": 0
    },
    {
        "_id": "60b606bd037113678862b58f",
        "title": "Official 27 Q2",
        "TPO": 27,
        "questionNumber": 2,
        "tag": "\u6559\u80b2\u5de5\u4f5c",
        "questionType": "Agree or Disagree",
        "questionType2": "Q2 \u8bdd\u9898\u5206\u7c7b",
        "userCount": 0,
        "tagCount": 0,
        "recordCount": 0
    },
    {
        "_id": "60b607c4037113678862b660",
        "title": "Official 27 Q3",
        "TPO": 27,
        "questionNumber": 3,
        "tag": "\u540e\u52e4\u670d\u52a1",
        "questionType": "\u7efc\u5408",
        "questionType2": "Q3 \u6821\u56ed\u573a\u666f",
        "userCount": 0,
        "tagCount": 29,
        "recordCount": 0
    },
    {
        "_id": "60b608b4037113678862b6d4",
        "title": "Official 27 Q4",
        "TPO": 27,
        "questionNumber": 4,
        "tag": "\u751f\u7269",
        "questionType": "\u7efc\u5408",
        "questionType2": "Q4&Q6 \u5b66\u672f\u7c7b\u8bb2\u5ea7",
        "userCount": 0,
        "tagCount": 27,
        "recordCount": 0
    },
    {
        "_id": "60b60980037113678862b705",
        "title": "Official 27 Q6",
        "TPO": 27,
        "questionNumber": 6,
        "tag": "\u5386\u53f2",
        "questionType": "\u7efc\u5408",
        "questionType2": "Q4&Q6 \u5b66\u672f\u7c7b\u8bb2\u5ea7",
        "userCount": 0,
        "tagCount": 22,
        "recordCount": 0
    },
    {
        "_id": "60b60a86037113678862b72a",
        "title": "Official 28 Q2",
        "TPO": 28,
        "questionNumber": 2,
        "tag": "\u793e\u4f1a\u8bdd\u9898",
        "questionType": "Agree or Disagree",
        "questionType2": "Q2 \u8bdd\u9898\u5206\u7c7b",
        "userCount": 0,
        "tagCount": 0,
        "recordCount": 0
    },
    {
        "_id": "60b60b7e037113678862b72c",
        "title": "Official 28 Q3",
        "TPO": 28,
        "questionNumber": 3,
        "tag": "\u57fa\u7840\u5efa\u8bbe",
        "questionType": "\u7efc\u5408",
        "questionType2": "Q3 \u6821\u56ed\u573a\u666f",
        "userCount": 0,
        "tagCount": 26,
        "recordCount": 0
    },
    {
        "_id": "60b60d6e037113678862b766",
        "title": "Official 28 Q4",
        "TPO": 28,
        "questionNumber": 4,
        "tag": "\u5546\u4e1a",
        "questionType": "\u7efc\u5408",
        "questionType2": "Q4&Q6 \u5b66\u672f\u7c7b\u8bb2\u5ea7",
        "userCount": 0,
        "tagCount": 18,
        "recordCount": 0
    },
    {
        "_id": "60b60e3f037113678862b7be",
        "title": "Official 28 Q6",
        "TPO": 28,
        "questionNumber": 6,
        "tag": "\u5730\u8d28",
        "questionType": "\u7efc\u5408",
        "questionType2": "Q4&Q6 \u5b66\u672f\u7c7b\u8bb2\u5ea7",
        "userCount": 0,
        "tagCount": 32,
        "recordCount": 0
    },
    {
        "_id": "60b61476037113678862b9ac",
        "title": "Official 29 Q2",
        "TPO": 29,
        "questionNumber": 2,
        "tag": "\u6559\u80b2\u5de5\u4f5c",
        "questionType": "\u4e8c\u9009\u4e00",
        "questionType2": "Q2 \u8bdd\u9898\u5206\u7c7b",
        "userCount": 0,
        "tagCount": 0,
        "recordCount": 0
    },
    {
        "_id": "60b61566037113678862bb21",
        "title": "Official 29 Q3",
        "TPO": 29,
        "questionNumber": 3,
        "tag": "\u57fa\u7840\u5efa\u8bbe",
        "questionType": "\u7efc\u5408",
        "questionType2": "Q3 \u6821\u56ed\u573a\u666f",
        "userCount": 0,
        "tagCount": 23,
        "recordCount": 0
    },
    {
        "_id": "60b61638037113678862bce3",
        "title": "Official 29 Q4",
        "TPO": 29,
        "questionNumber": 4,
        "tag": "\u751f\u7269",
        "questionType": "\u7efc\u5408",
        "questionType2": "Q4&Q6 \u5b66\u672f\u7c7b\u8bb2\u5ea7",
        "userCount": 0,
        "tagCount": 25,
        "recordCount": 0
    },
    {
        "_id": "60b616fd037113678862bdfc",
        "title": "Official 29 Q6",
        "TPO": 29,
        "questionNumber": 6,
        "tag": "\u5546\u4e1a",
        "questionType": "\u7efc\u5408",
        "questionType2": "Q4&Q6 \u5b66\u672f\u7c7b\u8bb2\u5ea7",
        "userCount": 0,
        "tagCount": 12,
        "recordCount": 0
    },
    {
        "_id": "60b6179e037113678862be45",
        "title": "Official 30 Q2",
        "TPO": 30,
        "questionNumber": 2,
        "tag": "\u6559\u80b2\u5de5\u4f5c",
        "questionType": "Agree or Disagree",
        "questionType2": "Q2 \u8bdd\u9898\u5206\u7c7b",
        "userCount": 0,
        "tagCount": 0,
        "recordCount": 0
    },
    {
        "_id": "60b61879037113678862be51",
        "title": "Official 30 Q3",
        "TPO": 30,
        "questionNumber": 3,
        "tag": "\u57fa\u7840\u5efa\u8bbe",
        "questionType": "\u7efc\u5408",
        "questionType2": "Q3 \u6821\u56ed\u573a\u666f",
        "userCount": 0,
        "tagCount": 0,
        "recordCount": 0
    },
    {
        "_id": "60b619d4037113678862be78",
        "title": "Official 30 Q4",
        "TPO": 30,
        "questionNumber": 4,
        "tag": "\u5fc3\u7406",
        "questionType": "\u7efc\u5408",
        "questionType2": "Q4&Q6 \u5b66\u672f\u7c7b\u8bb2\u5ea7",
        "userCount": 0,
        "tagCount": 0,
        "recordCount": 0
    },
    {
        "_id": "60b61aa5037113678862beae",
        "title": "Official 30 Q6",
        "TPO": 30,
        "questionNumber": 6,
        "tag": "\u751f\u7269",
        "questionType": "\u7efc\u5408",
        "questionType2": "Q4&Q6 \u5b66\u672f\u7c7b\u8bb2\u5ea7",
        "userCount": 0,
        "tagCount": 0,
        "recordCount": 0
    },
    {
        "_id": "61caa57e84804fcbb14e81b4",
        "title": "Official 32 Q2",
        "TPO": 32,
        "questionNumber": 2,
        "tag": "\u793e\u4f1a\u8bdd\u9898",
        "questionType": "Agree or Disagree",
        "questionType2": "Q2 \u8bdd\u9898\u5206\u7c7b",
        "userCount": 0,
        "tagCount": 0,
        "recordCount": 0
    },
    {
        "_id": "61caac0a84804fcbb14ea32b",
        "title": "Official 32 Q3",
        "TPO": 32,
        "questionNumber": 3,
        "tag": "\u57fa\u7840\u5efa\u8bbe",
        "questionType": "\u7efc\u5408",
        "questionType2": "Q3 \u6821\u56ed\u573a\u666f",
        "userCount": 0,
        "tagCount": 0,
        "recordCount": 0
    },
    {
        "_id": "61caaf4e84804fcbb14eaab1",
        "title": "Official 32 Q4",
        "TPO": 32,
        "questionNumber": 4,
        "tag": "\u5fc3\u7406",
        "questionType": "\u7efc\u5408",
        "questionType2": "Q4&Q6 \u5b66\u672f\u7c7b\u8bb2\u5ea7",
        "userCount": 0,
        "tagCount": 0,
        "recordCount": 0
    },
    {
        "_id": "61cab06b84804fcbb14eac08",
        "title": "Official 32 Q6",
        "TPO": 32,
        "questionNumber": 6,
        "tag": "\u73af\u5883",
        "questionType": "\u7efc\u5408",
        "questionType2": "Q4&Q6 \u5b66\u672f\u7c7b\u8bb2\u5ea7",
        "userCount": 0,
        "tagCount": 0,
        "recordCount": 0
    },
    {
        "_id": "61cab1da84804fcbb14eaf86",
        "title": "Official 33 Q2",
        "TPO": 33,
        "questionNumber": 2,
        "tag": "\u793e\u4f1a\u8bdd\u9898",
        "questionType": "Agree or Disagree",
        "questionType2": "Q2 \u8bdd\u9898\u5206\u7c7b",
        "userCount": 0,
        "tagCount": 0,
        "recordCount": 0
    },
    {
        "_id": "61cab2ef84804fcbb14eb156",
        "title": "Official 33 Q3",
        "TPO": 33,
        "questionNumber": 3,
        "tag": "\u57fa\u7840\u5efa\u8bbe",
        "questionType": "\u7efc\u5408",
        "questionType2": "Q3 \u6821\u56ed\u573a\u666f",
        "userCount": 0,
        "tagCount": 15,
        "recordCount": 0
    },
    {
        "_id": "61cab42c84804fcbb14eb2a8",
        "title": "Official 33 Q4",
        "TPO": 33,
        "questionNumber": 4,
        "tag": "\u751f\u7269",
        "questionType": "\u7efc\u5408",
        "questionType2": "Q4&Q6 \u5b66\u672f\u7c7b\u8bb2\u5ea7",
        "userCount": 0,
        "tagCount": 23,
        "recordCount": 0
    },
    {
        "_id": "61cab55084804fcbb14eb43f",
        "title": "Official 33 Q6",
        "TPO": 33,
        "questionNumber": 6,
        "tag": "\u5546\u79d1",
        "questionType": "\u7efc\u5408",
        "questionType2": "Q4&Q6 \u5b66\u672f\u7c7b\u8bb2\u5ea7",
        "userCount": 0,
        "tagCount": 15,
        "recordCount": 0
    },
    {
        "_id": "61cab65884804fcbb14ebbe4",
        "title": "Official 34 Q2",
        "TPO": 34,
        "questionNumber": 2,
        "tag": "\u793e\u4f1a\u8bdd\u9898",
        "questionType": "Agree or Disagree",
        "questionType2": "Q2 \u8bdd\u9898\u5206\u7c7b",
        "userCount": 0,
        "tagCount": 0,
        "recordCount": 0
    },
    {
        "_id": "61cab87a84804fcbb14ef441",
        "title": "Official 34 Q3",
        "TPO": 34,
        "questionNumber": 3,
        "tag": "\u6559\u5b66\u5b89\u6392",
        "questionType": "\u7efc\u5408",
        "questionType2": "Q3 \u6821\u56ed\u573a\u666f",
        "userCount": 0,
        "tagCount": 15,
        "recordCount": 0
    },
    {
        "_id": "61caba9184804fcbb14f1e58",
        "title": "Official 34 Q4",
        "TPO": 34,
        "questionNumber": 4,
        "tag": "\u5fc3\u7406",
        "questionType": "\u7efc\u5408",
        "questionType2": "Q4&Q6 \u5b66\u672f\u7c7b\u8bb2\u5ea7",
        "userCount": 0,
        "tagCount": 22,
        "recordCount": 0
    },
    {
        "_id": "61cabb9f84804fcbb14f3c21",
        "title": "Official 34 Q6",
        "TPO": 34,
        "questionNumber": 6,
        "tag": "\u751f\u7269",
        "questionType": "\u7efc\u5408",
        "questionType2": "Q4&Q6 \u5b66\u672f\u7c7b\u8bb2\u5ea7",
        "userCount": 0,
        "tagCount": 14,
        "recordCount": 0
    },
    {
        "_id": "61cabc7884804fcbb14f61e6",
        "title": "Official 35 Q2",
        "TPO": 35,
        "questionNumber": 2,
        "tag": "\u6559\u80b2\u5de5\u4f5c",
        "questionType": "Agree or Disagree",
        "questionType2": "Q2 \u8bdd\u9898\u5206\u7c7b",
        "userCount": 0,
        "tagCount": 0,
        "recordCount": 0
    },
    {
        "_id": "61cabdbd84804fcbb14f6b40",
        "title": "Official 35 Q3",
        "TPO": 35,
        "questionNumber": 3,
        "tag": "\u6559\u5b66\u5b89\u6392",
        "questionType": "\u7efc\u5408",
        "questionType2": "Q3 \u6821\u56ed\u573a\u666f",
        "userCount": 0,
        "tagCount": 15,
        "recordCount": 0
    },
    {
        "_id": "61cabec684804fcbb14f8a76",
        "title": "Official 35 Q4",
        "TPO": 35,
        "questionNumber": 4,
        "tag": "\u73af\u5883",
        "questionType": "\u7efc\u5408",
        "questionType2": "Q4&Q6 \u5b66\u672f\u7c7b\u8bb2\u5ea7",
        "userCount": 0,
        "tagCount": 21,
        "recordCount": 0
    },
    {
        "_id": "61cabfbe84804fcbb14f9e4d",
        "title": "Official 35 Q6",
        "TPO": 35,
        "questionNumber": 6,
        "tag": "\u5efa\u7b51",
        "questionType": "\u7efc\u5408",
        "questionType2": "Q4&Q6 \u5b66\u672f\u7c7b\u8bb2\u5ea7",
        "userCount": 0,
        "tagCount": 0,
        "recordCount": 0
    },
    {
        "_id": "61cac8616b7ac18f6757220a",
        "title": "Official 36 Q2",
        "TPO": 36,
        "questionNumber": 2,
        "tag": "\u751f\u6d3b\u65b9\u5f0f",
        "questionType": "Agree or Disagree",
        "questionType2": "Q2 \u8bdd\u9898\u5206\u7c7b",
        "userCount": 0,
        "tagCount": 0,
        "recordCount": 0
    },
    {
        "_id": "61cad474da517c304db510e6",
        "title": "Official 36 Q3",
        "TPO": 36,
        "questionNumber": 3,
        "tag": "\u8bfe\u7a0b\u5b89\u6392",
        "questionType": "\u7efc\u5408",
        "questionType2": "Q3 \u6821\u56ed\u573a\u666f",
        "userCount": 0,
        "tagCount": 14,
        "recordCount": 0
    },
    {
        "_id": "61cad938da517c304db53f33",
        "title": "Official 36 Q4",
        "TPO": 36,
        "questionNumber": 4,
        "tag": "\u827a\u672f",
        "questionType": "\u7efc\u5408",
        "questionType2": "Q4&Q6 \u5b66\u672f\u7c7b\u8bb2\u5ea7",
        "userCount": 0,
        "tagCount": 24,
        "recordCount": 0
    },
    {
        "_id": "61cadd4dda517c304db58822",
        "title": "Official 36 Q6",
        "TPO": 36,
        "questionNumber": 6,
        "tag": "\u751f\u7269",
        "questionType": "\u7efc\u5408",
        "questionType2": "Q4&Q6 \u5b66\u672f\u7c7b\u8bb2\u5ea7",
        "userCount": 0,
        "tagCount": 20,
        "recordCount": 0
    },
    {
        "_id": "61cadf8eda517c304db595b5",
        "title": "Official 37 Q2",
        "TPO": 37,
        "questionNumber": 2,
        "tag": "\u6559\u80b2\u5de5\u4f5c",
        "questionType": "Agree or Disagree",
        "questionType2": "Q2 \u8bdd\u9898\u5206\u7c7b",
        "userCount": 0,
        "tagCount": 0,
        "recordCount": 0
    },
    {
        "_id": "61cae0a2da517c304db5a192",
        "title": "Official 37 Q3",
        "TPO": 37,
        "questionNumber": 3,
        "tag": "\u540e\u52e4\u670d\u52a1",
        "questionType": "\u7efc\u5408",
        "questionType2": "Q3 \u6821\u56ed\u573a\u666f",
        "userCount": 0,
        "tagCount": 16,
        "recordCount": 0
    },
    {
        "_id": "61cae5c7da517c304db5da53",
        "title": "Official 37 Q4",
        "TPO": 37,
        "questionNumber": 4,
        "tag": "\u751f\u7269",
        "questionType": "\u7efc\u5408",
        "questionType2": "Q4&Q6 \u5b66\u672f\u7c7b\u8bb2\u5ea7",
        "userCount": 0,
        "tagCount": 23,
        "recordCount": 0
    },
    {
        "_id": "61cae845da517c304db5e347",
        "title": "Official 37 Q6",
        "TPO": 37,
        "questionNumber": 6,
        "tag": "\u827a\u672f",
        "questionType": "\u7efc\u5408",
        "questionType2": "Q4&Q6 \u5b66\u672f\u7c7b\u8bb2\u5ea7",
        "userCount": 0,
        "tagCount": 14,
        "recordCount": 0
    },
    {
        "_id": "61cbc2dada517c304ddc84d5",
        "title": "Official 38 Q2",
        "TPO": 38,
        "questionNumber": 2,
        "tag": "\u751f\u6d3b\u65b9\u5f0f",
        "questionType": "Agree or Disagree",
        "questionType2": "Q2 \u8bdd\u9898\u5206\u7c7b",
        "userCount": 0,
        "tagCount": 0,
        "recordCount": 0
    },
    {
        "_id": "61cbc415da517c304ddc9fb0",
        "title": "Official 38 Q3",
        "TPO": 38,
        "questionNumber": 3,
        "tag": "\u8bfe\u5916\u6d3b\u52a8",
        "questionType": "\u7efc\u5408",
        "questionType2": "Q3 \u6821\u56ed\u573a\u666f",
        "userCount": 0,
        "tagCount": 23,
        "recordCount": 0
    },
    {
        "_id": "61cbc533da517c304ddcab50",
        "title": "Official 38 Q4",
        "TPO": 38,
        "questionNumber": 4,
        "tag": "\u751f\u7269",
        "questionType": "\u7efc\u5408",
        "questionType2": "Q4&Q6 \u5b66\u672f\u7c7b\u8bb2\u5ea7",
        "userCount": 0,
        "tagCount": 25,
        "recordCount": 0
    },
    {
        "_id": "61cbc63ada517c304ddcaf53",
        "title": "Official 38 Q6",
        "TPO": 38,
        "questionNumber": 6,
        "tag": "\u5efa\u7b51",
        "questionType": "\u7efc\u5408",
        "questionType2": "Q4&Q6 \u5b66\u672f\u7c7b\u8bb2\u5ea7",
        "userCount": 0,
        "tagCount": 16,
        "recordCount": 0
    },
    {
        "_id": "61cbc799da517c304ddccd02",
        "title": "Official 39 Q2",
        "TPO": 39,
        "questionNumber": 2,
        "tag": "\u6559\u80b2\u5de5\u4f5c",
        "questionType": "\u4e8c\u9009\u4e00",
        "questionType2": "Q2 \u8bdd\u9898\u5206\u7c7b",
        "userCount": 0,
        "tagCount": 0,
        "recordCount": 0
    },
    {
        "_id": "61cbcec4da517c304dde3ca0",
        "title": "Official 39 Q3",
        "TPO": 39,
        "questionNumber": 3,
        "tag": "\u540e\u52e4\u670d\u52a1",
        "questionType": "\u7efc\u5408",
        "questionType2": "Q3 \u6821\u56ed\u573a\u666f",
        "userCount": 0,
        "tagCount": 20,
        "recordCount": 0
    },
    {
        "_id": "61cbd08bda517c304dde62aa",
        "title": "Official 39 Q4",
        "TPO": 39,
        "questionNumber": 4,
        "tag": "\u5546\u4e1a",
        "questionType": "\u7efc\u5408",
        "questionType2": "Q4&Q6 \u5b66\u672f\u7c7b\u8bb2\u5ea7",
        "userCount": 0,
        "tagCount": 27,
        "recordCount": 0
    },
    {
        "_id": "61cbd1b1da517c304dde70a3",
        "title": "Official 39 Q6",
        "TPO": 39,
        "questionNumber": 6,
        "tag": "\u751f\u7269",
        "questionType": "\u7efc\u5408",
        "questionType2": "Q4&Q6 \u5b66\u672f\u7c7b\u8bb2\u5ea7",
        "userCount": 0,
        "tagCount": 14,
        "recordCount": 0
    },
    {
        "_id": "61cbd363da517c304dde8a36",
        "title": "Official 40 Q2",
        "TPO": 40,
        "questionNumber": 2,
        "tag": "\u793e\u4f1a\u8bdd\u9898",
        "questionType": "\u4e8c\u9009\u4e00",
        "questionType2": "Q2 \u8bdd\u9898\u5206\u7c7b",
        "userCount": 0,
        "tagCount": 0,
        "recordCount": 0
    },
    {
        "_id": "61cbd471da517c304ddea34b",
        "title": "Official 40 Q3",
        "TPO": 40,
        "questionNumber": 3,
        "tag": "\u540e\u52e4\u670d\u52a1",
        "questionType": "\u7efc\u5408",
        "questionType2": "Q3 \u6821\u56ed\u573a\u666f",
        "userCount": 0,
        "tagCount": 13,
        "recordCount": 0
    },
    {
        "_id": "61cbd679da517c304dded231",
        "title": "Official 40 Q4",
        "TPO": 40,
        "questionNumber": 4,
        "tag": "\u751f\u7269",
        "questionType": "\u7efc\u5408",
        "questionType2": "Q4&Q6 \u5b66\u672f\u7c7b\u8bb2\u5ea7",
        "userCount": 0,
        "tagCount": 21,
        "recordCount": 0
    },
    {
        "_id": "61cbd791da517c304ddede6b",
        "title": "Official 40 Q6",
        "TPO": 40,
        "questionNumber": 6,
        "tag": "\u5546\u79d1",
        "questionType": "\u7efc\u5408",
        "questionType2": "Q4&Q6 \u5b66\u672f\u7c7b\u8bb2\u5ea7",
        "userCount": 0,
        "tagCount": 13,
        "recordCount": 0
    },
    {
        "_id": "61cbd99ada517c304ddf43b3",
        "title": "Official 41 Q2",
        "TPO": 41,
        "questionNumber": 2,
        "tag": "\u6559\u80b2\u5de5\u4f5c",
        "questionType": "\u4e8c\u9009\u4e00",
        "questionType2": "Q2 \u8bdd\u9898\u5206\u7c7b",
        "userCount": 0,
        "tagCount": 0,
        "recordCount": 0
    },
    {
        "_id": "61cbdab1da517c304ddf50b9",
        "title": "Official 41 Q3",
        "TPO": 41,
        "questionNumber": 3,
        "tag": "\u6559\u5b66\u5b89\u6392",
        "questionType": "\u7efc\u5408",
        "questionType2": "Q3 \u6821\u56ed\u573a\u666f",
        "userCount": 0,
        "tagCount": 15,
        "recordCount": 0
    },
    {
        "_id": "61cbdc64da517c304ddf836c",
        "title": "Official 41 Q4",
        "TPO": 41,
        "questionNumber": 4,
        "tag": "\u5fc3\u7406",
        "questionType": "\u7efc\u5408",
        "questionType2": "Q4&Q6 \u5b66\u672f\u7c7b\u8bb2\u5ea7",
        "userCount": 0,
        "tagCount": 17,
        "recordCount": 0
    },
    {
        "_id": "61cbdd42da517c304ddf88aa",
        "title": "Official 41 Q6",
        "TPO": 41,
        "questionNumber": 6,
        "tag": "\u5fc3\u7406",
        "questionType": "\u7efc\u5408",
        "questionType2": "Q4&Q6 \u5b66\u672f\u7c7b\u8bb2\u5ea7",
        "userCount": 0,
        "tagCount": 14,
        "recordCount": 0
    },
    {
        "_id": "61cbf5a6da517c304de0d7a3",
        "title": "Official 42 Q2",
        "TPO": 42,
        "questionNumber": 2,
        "tag": "\u751f\u6d3b\u65b9\u5f0f",
        "questionType": "\u4e8c\u9009\u4e00",
        "questionType2": "Q2 \u8bdd\u9898\u5206\u7c7b",
        "userCount": 0,
        "tagCount": 0,
        "recordCount": 0
    },
    {
        "_id": "61cbf6c7da517c304de0d815",
        "title": "Official 42 Q3",
        "TPO": 42,
        "questionNumber": 3,
        "tag": "\u6559\u5b66\u5b89\u6392",
        "questionType": "\u7efc\u5408",
        "questionType2": "Q3 \u6821\u56ed\u573a\u666f",
        "userCount": 0,
        "tagCount": 14,
        "recordCount": 0
    },
    {
        "_id": "61cbf7e3da517c304de0da16",
        "title": "Official 42 Q4",
        "TPO": 42,
        "questionNumber": 4,
        "tag": "\u751f\u7269",
        "questionType": "\u7efc\u5408",
        "questionType2": "Q4&Q6 \u5b66\u672f\u7c7b\u8bb2\u5ea7",
        "userCount": 0,
        "tagCount": 10,
        "recordCount": 0
    },
    {
        "_id": "61cbf8c3da517c304de0e5da",
        "title": "Official 42 Q6",
        "TPO": 42,
        "questionNumber": 6,
        "tag": "\u73af\u5883",
        "questionType": "\u7efc\u5408",
        "questionType2": "Q4&Q6 \u5b66\u672f\u7c7b\u8bb2\u5ea7",
        "userCount": 0,
        "tagCount": 15,
        "recordCount": 0
    },
    {
        "_id": "61cbf997da517c304de0f1d2",
        "title": "Official 43 Q2",
        "TPO": 43,
        "questionNumber": 2,
        "tag": "\u6559\u80b2\u5de5\u4f5c",
        "questionType": "\u4e8c\u9009\u4e00",
        "questionType2": "Q2 \u8bdd\u9898\u5206\u7c7b",
        "userCount": 0,
        "tagCount": 0,
        "recordCount": 0
    },
    {
        "_id": "61cbfac2da517c304de0fb87",
        "title": "Official 43 Q3",
        "TPO": 43,
        "questionNumber": 3,
        "tag": "\u8bfe\u5916\u6d3b\u52a8",
        "questionType": "\u7efc\u5408",
        "questionType2": "Q3 \u6821\u56ed\u573a\u666f",
        "userCount": 0,
        "tagCount": 11,
        "recordCount": 0
    },
    {
        "_id": "61cbfbc8da517c304de10892",
        "title": "Official 43 Q4",
        "TPO": 43,
        "questionNumber": 4,
        "tag": "\u751f\u7269",
        "questionType": "\u7efc\u5408",
        "questionType2": "Q4&Q6 \u5b66\u672f\u7c7b\u8bb2\u5ea7",
        "userCount": 0,
        "tagCount": 21,
        "recordCount": 0
    },
    {
        "_id": "61cbfcbcda517c304de1167f",
        "title": "Official 43 Q6",
        "TPO": 43,
        "questionNumber": 6,
        "tag": "\u751f\u7269",
        "questionType": "\u7efc\u5408",
        "questionType2": "Q4&Q6 \u5b66\u672f\u7c7b\u8bb2\u5ea7",
        "userCount": 0,
        "tagCount": 10,
        "recordCount": 0
    },
    {
        "_id": "61cc0221da517c304de16247",
        "title": "Official 44 Q2",
        "TPO": 44,
        "questionNumber": 2,
        "tag": "\u6559\u80b2\u5de5\u4f5c",
        "questionType": "\u4e8c\u9009\u4e00",
        "questionType2": "Q2 \u8bdd\u9898\u5206\u7c7b",
        "userCount": 0,
        "tagCount": 0,
        "recordCount": 0
    },
    {
        "_id": "61cc0457da517c304de17724",
        "title": "Official 44 Q3",
        "TPO": 44,
        "questionNumber": 3,
        "tag": "\u8bfe\u5916\u6d3b\u52a8",
        "questionType": "\u7efc\u5408",
        "questionType2": "Q3 \u6821\u56ed\u573a\u666f",
        "userCount": 0,
        "tagCount": 16,
        "recordCount": 0
    },
    {
        "_id": "61cc05cdda517c304de184a5",
        "title": "Official 44 Q4",
        "TPO": 44,
        "questionNumber": 4,
        "tag": "\u5546\u4e1a",
        "questionType": "\u7efc\u5408",
        "questionType2": "Q4&Q6 \u5b66\u672f\u7c7b\u8bb2\u5ea7",
        "userCount": 0,
        "tagCount": 14,
        "recordCount": 0
    },
    {
        "_id": "61cc0714da517c304de18ddb",
        "title": "Official 44 Q6",
        "TPO": 44,
        "questionNumber": 6,
        "tag": "\u751f\u7269",
        "questionType": "\u7efc\u5408",
        "questionType2": "Q4&Q6 \u5b66\u672f\u7c7b\u8bb2\u5ea7",
        "userCount": 0,
        "tagCount": 7,
        "recordCount": 0
    },
    {
        "_id": "61cc08a4f2e6da5d90af68c2",
        "title": "Official 45 Q2",
        "TPO": 45,
        "questionNumber": 2,
        "tag": "\u793e\u4f1a\u8bdd\u9898",
        "questionType": "Agree or Disagree",
        "questionType2": "Q2 \u8bdd\u9898\u5206\u7c7b",
        "userCount": 0,
        "tagCount": 0,
        "recordCount": 0
    },
    {
        "_id": "61cc09ebf2e6da5d90af86ce",
        "title": "Official 45 Q3",
        "TPO": 45,
        "questionNumber": 3,
        "tag": "\u540e\u52e4\u670d\u52a1",
        "questionType": "\u7efc\u5408",
        "questionType2": "Q3 \u6821\u56ed\u573a\u666f",
        "userCount": 0,
        "tagCount": 14,
        "recordCount": 0
    },
    {
        "_id": "61cc0ae0f2e6da5d90af98aa",
        "title": "Official 45 Q4",
        "TPO": 45,
        "questionNumber": 4,
        "tag": "\u5fc3\u7406",
        "questionType": "\u7efc\u5408",
        "questionType2": "Q4&Q6 \u5b66\u672f\u7c7b\u8bb2\u5ea7",
        "userCount": 0,
        "tagCount": 23,
        "recordCount": 0
    },
    {
        "_id": "61cc0bd4f2e6da5d90afda0c",
        "title": "Official 45 Q6",
        "TPO": 45,
        "questionNumber": 6,
        "tag": "\u751f\u7269",
        "questionType": "\u7efc\u5408",
        "questionType2": "Q4&Q6 \u5b66\u672f\u7c7b\u8bb2\u5ea7",
        "userCount": 0,
        "tagCount": 12,
        "recordCount": 0
    },
    {
        "_id": "61cc0d27f2e6da5d90aff493",
        "title": "Official 46 Q2",
        "TPO": 46,
        "questionNumber": 2,
        "tag": "\u793e\u4f1a\u8bdd\u9898",
        "questionType": "Agree or Disagree",
        "questionType2": "Q2 \u8bdd\u9898\u5206\u7c7b",
        "userCount": 0,
        "tagCount": 0,
        "recordCount": 0
    },
    {
        "_id": "61cc0e2ef2e6da5d90b00ebc",
        "title": "Official 46 Q3",
        "TPO": 46,
        "questionNumber": 3,
        "tag": "\u8bfe\u5916\u6d3b\u52a8",
        "questionType": "\u7efc\u5408",
        "questionType2": "Q3 \u6821\u56ed\u573a\u666f",
        "userCount": 0,
        "tagCount": 15,
        "recordCount": 0
    },
    {
        "_id": "61cc115df2e6da5d90b01526",
        "title": "Official 46 Q4",
        "TPO": 46,
        "questionNumber": 4,
        "tag": "\u751f\u7269",
        "questionType": "\u7efc\u5408",
        "questionType2": "Q4&Q6 \u5b66\u672f\u7c7b\u8bb2\u5ea7",
        "userCount": 0,
        "tagCount": 17,
        "recordCount": 0
    },
    {
        "_id": "61cc1274f2e6da5d90b01827",
        "title": "Official 46 Q6",
        "TPO": 46,
        "questionNumber": 6,
        "tag": "\u5fc3\u7406",
        "questionType": "\u7efc\u5408",
        "questionType2": "Q4&Q6 \u5b66\u672f\u7c7b\u8bb2\u5ea7",
        "userCount": 0,
        "tagCount": 9,
        "recordCount": 0
    },
    {
        "_id": "61cc168df2e6da5d90b092e3",
        "title": "Official 47 Q2",
        "TPO": 47,
        "questionNumber": 2,
        "tag": "\u6559\u80b2\u5de5\u4f5c",
        "questionType": "Agree or Disagree",
        "questionType2": "Q2 \u8bdd\u9898\u5206\u7c7b",
        "userCount": 0,
        "tagCount": 0,
        "recordCount": 0
    },
    {
        "_id": "61cc188df2e6da5d90b0a7cb",
        "title": "Official 47 Q3",
        "TPO": 47,
        "questionNumber": 3,
        "tag": "\u8bfe\u7a0b\u5b89\u6392",
        "questionType": "\u7efc\u5408",
        "questionType2": "Q3 \u6821\u56ed\u573a\u666f",
        "userCount": 0,
        "tagCount": 13,
        "recordCount": 0
    },
    {
        "_id": "61cc1a59f2e6da5d90b0e30f",
        "title": "Official 47 Q4",
        "TPO": 47,
        "questionNumber": 4,
        "tag": "\u5fc3\u7406",
        "questionType": "\u7efc\u5408",
        "questionType2": "Q4&Q6 \u5b66\u672f\u7c7b\u8bb2\u5ea7",
        "userCount": 0,
        "tagCount": 14,
        "recordCount": 0
    },
    {
        "_id": "61cc1b76f2e6da5d90b0e69b",
        "title": "Official 47 Q6",
        "TPO": 47,
        "questionNumber": 6,
        "tag": "\u5386\u53f2",
        "questionType": "\u7efc\u5408",
        "questionType2": "Q4&Q6 \u5b66\u672f\u7c7b\u8bb2\u5ea7",
        "userCount": 0,
        "tagCount": 10,
        "recordCount": 0
    },
    {
        "_id": "61cc1ee8f2e6da5d90b102b9",
        "title": "Official 48 Q2",
        "TPO": 48,
        "questionNumber": 2,
        "tag": "\u751f\u6d3b\u65b9\u5f0f",
        "questionType": "\u4e8c\u9009\u4e00",
        "questionType2": "Q2 \u8bdd\u9898\u5206\u7c7b",
        "userCount": 0,
        "tagCount": 0,
        "recordCount": 0
    },
    {
        "_id": "61cc204af2e6da5d90b108cd",
        "title": "Official 48 Q3",
        "TPO": 48,
        "questionNumber": 3,
        "tag": "\u57fa\u7840\u5efa\u8bbe",
        "questionType": "\u7efc\u5408",
        "questionType2": "Q3 \u6821\u56ed\u573a\u666f",
        "userCount": 0,
        "tagCount": 18,
        "recordCount": 0
    },
    {
        "_id": "61cc219df2e6da5d90b1252f",
        "title": "Official 48 Q4",
        "TPO": 48,
        "questionNumber": 4,
        "tag": "\u751f\u7269",
        "questionType": "\u7efc\u5408",
        "questionType2": "Q4&Q6 \u5b66\u672f\u7c7b\u8bb2\u5ea7",
        "userCount": 0,
        "tagCount": 18,
        "recordCount": 0
    },
    {
        "_id": "61cc22adf2e6da5d90b13110",
        "title": "Official 48 Q6",
        "TPO": 48,
        "questionNumber": 6,
        "tag": "\u73af\u5883",
        "questionType": "\u7efc\u5408",
        "questionType2": "Q4&Q6 \u5b66\u672f\u7c7b\u8bb2\u5ea7",
        "userCount": 0,
        "tagCount": 18,
        "recordCount": 0
    },
    {
        "_id": "61cc254ff2e6da5d90b140be",
        "title": "Official 49 Q2",
        "TPO": 49,
        "questionNumber": 2,
        "tag": "\u6559\u80b2\u5de5\u4f5c",
        "questionType": "\u4e8c\u9009\u4e00",
        "questionType2": "Q2 \u8bdd\u9898\u5206\u7c7b",
        "userCount": 0,
        "tagCount": 0,
        "recordCount": 0
    },
    {
        "_id": "61cc2737f2e6da5d90b14ede",
        "title": "Official 49 Q3",
        "TPO": 49,
        "questionNumber": 3,
        "tag": "\u8bfe\u7a0b\u5b89\u6392",
        "questionType": "\u7efc\u5408",
        "questionType2": "Q3 \u6821\u56ed\u573a\u666f",
        "userCount": 0,
        "tagCount": 18,
        "recordCount": 0
    },
    {
        "_id": "61cc2934f2e6da5d90b15b83",
        "title": "Official 49 Q4",
        "TPO": 49,
        "questionNumber": 4,
        "tag": "\u5fc3\u7406",
        "questionType": "\u7efc\u5408",
        "questionType2": "Q4&Q6 \u5b66\u672f\u7c7b\u8bb2\u5ea7",
        "userCount": 0,
        "tagCount": 10,
        "recordCount": 0
    },
    {
        "_id": "61cc2a5bf2e6da5d90b16722",
        "title": "Official 49 Q6",
        "TPO": 49,
        "questionNumber": 6,
        "tag": "\u751f\u7269",
        "questionType": "\u7efc\u5408",
        "questionType2": "Q4&Q6 \u5b66\u672f\u7c7b\u8bb2\u5ea7",
        "userCount": 0,
        "tagCount": 10,
        "recordCount": 0
    },
    {
        "_id": "61cc2b93f2e6da5d90b17393",
        "title": "Official 50 Q2",
        "TPO": 50,
        "questionNumber": 2,
        "tag": "\u751f\u6d3b\u65b9\u5f0f",
        "questionType": "\u4e8c\u9009\u4e00",
        "questionType2": "Q2 \u8bdd\u9898\u5206\u7c7b",
        "userCount": 0,
        "tagCount": 0,
        "recordCount": 0
    },
    {
        "_id": "61cc2f97f2e6da5d90b1b627",
        "title": "Official 50 Q3",
        "TPO": 50,
        "questionNumber": 3,
        "tag": "\u540e\u52e4\u670d\u52a1",
        "questionType": "\u7efc\u5408",
        "questionType2": "Q3 \u6821\u56ed\u573a\u666f",
        "userCount": 0,
        "tagCount": 18,
        "recordCount": 0
    },
    {
        "_id": "61cc3178f2e6da5d90b1d1f6",
        "title": "Official 50 Q4",
        "TPO": 50,
        "questionNumber": 4,
        "tag": "\u5fc3\u7406",
        "questionType": "\u7efc\u5408",
        "questionType2": "Q4&Q6 \u5b66\u672f\u7c7b\u8bb2\u5ea7",
        "userCount": 0,
        "tagCount": 22,
        "recordCount": 0
    },
    {
        "_id": "61cc340ef2e6da5d90b20877",
        "title": "Official 50 Q6",
        "TPO": 50,
        "questionNumber": 6,
        "tag": "\u751f\u7269",
        "questionType": "\u7efc\u5408",
        "questionType2": "Q4&Q6 \u5b66\u672f\u7c7b\u8bb2\u5ea7",
        "userCount": 0,
        "tagCount": 22,
        "recordCount": 0
    },
    {
        "_id": "61cc37fff2e6da5d90b2424c",
        "title": "Official 51 Q2",
        "TPO": 51,
        "questionNumber": 2,
        "tag": "\u793e\u4f1a\u8bdd\u9898",
        "questionType": "Agree or Disagree",
        "questionType2": "Q2 \u8bdd\u9898\u5206\u7c7b",
        "userCount": 0,
        "tagCount": 0,
        "recordCount": 0
    },
    {
        "_id": "61cc49eaf2e6da5d90b32fde",
        "title": "Official 51 Q3",
        "TPO": 51,
        "questionNumber": 3,
        "tag": "\u6821\u56ed\u5efa\u8bbe",
        "questionType": "\u7efc\u5408",
        "questionType2": "Q3 \u6821\u56ed\u573a\u666f",
        "userCount": 0,
        "tagCount": 25,
        "recordCount": 0
    },
    {
        "_id": "61cd0d28f2e6da5d90d9e6cf",
        "title": "Official 51 Q4",
        "TPO": 51,
        "questionNumber": 4,
        "tag": "\u5546\u4e1a",
        "questionType": "\u7efc\u5408",
        "questionType2": "Q4&Q6 \u5b66\u672f\u7c7b\u8bb2\u5ea7",
        "userCount": 0,
        "tagCount": 20,
        "recordCount": 0
    },
    {
        "_id": "61cd0dedf2e6da5d90d9ec1a",
        "title": "Official 51 Q6",
        "TPO": 51,
        "questionNumber": 6,
        "tag": "\u751f\u7269",
        "questionType": "\u7efc\u5408",
        "questionType2": "Q4&Q6 \u5b66\u672f\u7c7b\u8bb2\u5ea7",
        "userCount": 0,
        "tagCount": 17,
        "recordCount": 0
    },
    {
        "_id": "61cd0ec7f2e6da5d90d9ef25",
        "title": "Official 52 Q2",
        "TPO": 52,
        "questionNumber": 2,
        "tag": "\u751f\u6d3b\u65b9\u5f0f",
        "questionType": "Agree or Disagree",
        "questionType2": "Q2 \u8bdd\u9898\u5206\u7c7b",
        "userCount": 0,
        "tagCount": 0,
        "recordCount": 0
    },
    {
        "_id": "61cd1053f2e6da5d90d9f25e",
        "title": "Official 52 Q3",
        "TPO": 52,
        "questionNumber": 3,
        "tag": "\u8bfe\u5916\u6d3b\u52a8",
        "questionType": "\u7efc\u5408",
        "questionType2": "Q3 \u6821\u56ed\u573a\u666f",
        "userCount": 0,
        "tagCount": 17,
        "recordCount": 0
    },
    {
        "_id": "61cd1129f2e6da5d90d9f9a2",
        "title": "Official 52 Q4",
        "TPO": 52,
        "questionNumber": 4,
        "tag": "\u793e\u4f1a\u5b66",
        "questionType": "\u7efc\u5408",
        "questionType2": "Q4&Q6 \u5b66\u672f\u7c7b\u8bb2\u5ea7",
        "userCount": 0,
        "tagCount": 20,
        "recordCount": 0
    },
    {
        "_id": "61cd11dff2e6da5d90d9fc90",
        "title": "Official 52 Q6",
        "TPO": 52,
        "questionNumber": 6,
        "tag": "\u73af\u5883",
        "questionType": "\u7efc\u5408",
        "questionType2": "Q4&Q6 \u5b66\u672f\u7c7b\u8bb2\u5ea7",
        "userCount": 0,
        "tagCount": 21,
        "recordCount": 0
    },
    {
        "_id": "61cd12a0f2e6da5d90da09a0",
        "title": "Official 53 Q2",
        "TPO": 53,
        "questionNumber": 2,
        "tag": "\u751f\u6d3b\u65b9\u5f0f",
        "questionType": "\u4e8c\u9009\u4e00",
        "questionType2": "Q2 \u8bdd\u9898\u5206\u7c7b",
        "userCount": 0,
        "tagCount": 0,
        "recordCount": 0
    },
    {
        "_id": "61cd1391f2e6da5d90da118a",
        "title": "Official 53 Q3",
        "TPO": 53,
        "questionNumber": 3,
        "tag": "\u540e\u52e4\u670d\u52a1",
        "questionType": "\u7efc\u5408",
        "questionType2": "Q3 \u6821\u56ed\u573a\u666f",
        "userCount": 0,
        "tagCount": 31,
        "recordCount": 0
    },
    {
        "_id": "61cd1481f2e6da5d90da1818",
        "title": "Official 53 Q4",
        "TPO": 53,
        "questionNumber": 4,
        "tag": "\u5fc3\u7406",
        "questionType": "\u7efc\u5408",
        "questionType2": "Q4&Q6 \u5b66\u672f\u7c7b\u8bb2\u5ea7",
        "userCount": 0,
        "tagCount": 33,
        "recordCount": 0
    },
    {
        "_id": "61cd152df2e6da5d90da1be1",
        "title": "Official 53 Q6",
        "TPO": 53,
        "questionNumber": 6,
        "tag": "\u751f\u7269",
        "questionType": "\u7efc\u5408",
        "questionType2": "Q4&Q6 \u5b66\u672f\u7c7b\u8bb2\u5ea7",
        "userCount": 0,
        "tagCount": 15,
        "recordCount": 0
    },
    {
        "_id": "61cd1791f2e6da5d90da2b26",
        "title": "Official 54 Q2",
        "TPO": 54,
        "questionNumber": 2,
        "tag": "\u4e2a\u4eba\u7ecf\u5386",
        "questionType": "\u4e8c\u9009\u4e00",
        "questionType2": "Q2 \u8bdd\u9898\u5206\u7c7b",
        "userCount": 0,
        "tagCount": 0,
        "recordCount": 0
    },
    {
        "_id": "61cd1887f2e6da5d90da2e72",
        "title": "Official 54 Q3",
        "TPO": 54,
        "questionNumber": 3,
        "tag": "\u8bfe\u5916\u6d3b\u52a8",
        "questionType": "\u7efc\u5408",
        "questionType2": "Q3 \u6821\u56ed\u573a\u666f",
        "userCount": 0,
        "tagCount": 0,
        "recordCount": 0
    },
    {
        "_id": "61cd19a1f2e6da5d90da3396",
        "title": "Official 54 Q4",
        "TPO": 54,
        "questionNumber": 4,
        "tag": "\u5546\u4e1a",
        "questionType": "\u7efc\u5408",
        "questionType2": "Q4&Q6 \u5b66\u672f\u7c7b\u8bb2\u5ea7",
        "userCount": 0,
        "tagCount": 0,
        "recordCount": 0
    },
    {
        "_id": "61cd1a67f2e6da5d90da364b",
        "title": "Official 54 Q6",
        "TPO": 54,
        "questionNumber": 6,
        "tag": "\u751f\u7269",
        "questionType": "\u7efc\u5408",
        "questionType2": "Q4&Q6 \u5b66\u672f\u7c7b\u8bb2\u5ea7",
        "userCount": 0,
        "tagCount": 0,
        "recordCount": 0
    },
    {
        "_id": "62130da6937d1067a2d7cdde",
        "title": "Official 55 Q2",
        "TPO": 55,
        "questionNumber": 2,
        "tag": "\u4f11\u95f2\u65f6\u95f4",
        "questionType": "\u4e8c\u9009\u4e00",
        "questionType2": "Q2 \u8bdd\u9898\u5206\u7c7b",
        "userCount": 0,
        "tagCount": 0,
        "recordCount": 0
    },
    {
        "_id": "621327cf937d1067a2da8b13",
        "title": "Official 55 Q3",
        "TPO": 55,
        "questionNumber": 3,
        "tag": "\u8bfe\u5916\u6d3b\u52a8",
        "questionType": "\u7efc\u5408",
        "questionType2": "Q3 \u6821\u56ed\u573a\u666f",
        "userCount": 0,
        "tagCount": 0,
        "recordCount": 0
    },
    {
        "_id": "621328e1937d1067a2dabae4",
        "title": "Official 55 Q4",
        "TPO": 55,
        "questionNumber": 4,
        "tag": "\u751f\u7269",
        "questionType": "\u7efc\u5408",
        "questionType2": "Q4&Q6 \u5b66\u672f\u7c7b\u8bb2\u5ea7",
        "userCount": 0,
        "tagCount": 0,
        "recordCount": 0
    },
    {
        "_id": "621329a0937d1067a2dac915",
        "title": "Official 55 Q6",
        "TPO": 55,
        "questionNumber": 6,
        "tag": "\u5fc3\u7406",
        "questionType": "\u7efc\u5408",
        "questionType2": "Q4&Q6 \u5b66\u672f\u7c7b\u8bb2\u5ea7",
        "userCount": 0,
        "tagCount": 0,
        "recordCount": 0
    },
    {
        "_id": "621334ec937d1067a2dea2fe",
        "title": "Official 56 Q2",
        "TPO": 56,
        "questionNumber": 2,
        "tag": "\u6280\u80fd",
        "questionType": "Agree or Disagree",
        "questionType2": "Q2 \u8bdd\u9898\u5206\u7c7b",
        "userCount": 0,
        "tagCount": 0,
        "recordCount": 0
    },
    {
        "_id": "62133776937d1067a2df2231",
        "title": "Official 56 Q3",
        "TPO": 56,
        "questionNumber": 3,
        "tag": "\u57fa\u7840\u5efa\u8bbe",
        "questionType": "\u7efc\u5408",
        "questionType2": "Q3 \u6821\u56ed\u573a\u666f",
        "userCount": 0,
        "tagCount": 0,
        "recordCount": 0
    },
    {
        "_id": "621338ce937d1067a2dfa60f",
        "title": "Official 56 Q4",
        "TPO": 56,
        "questionNumber": 4,
        "tag": "\u751f\u7269",
        "questionType": "\u7efc\u5408",
        "questionType2": "Q4&Q6 \u5b66\u672f\u7c7b\u8bb2\u5ea7",
        "userCount": 0,
        "tagCount": 0,
        "recordCount": 0
    },
    {
        "_id": "62133985937d1067a2dfb232",
        "title": "Official 56 Q6",
        "TPO": 56,
        "questionNumber": 6,
        "tag": "\u5546\u4e1a",
        "questionType": "\u7efc\u5408",
        "questionType2": "Q4&Q6 \u5b66\u672f\u7c7b\u8bb2\u5ea7",
        "userCount": 0,
        "tagCount": 0,
        "recordCount": 0
    },
    {
        "_id": "62382cd0051b20466f375a25",
        "title": "Official 57 Q2",
        "TPO": 57,
        "questionNumber": 2,
        "tag": "\u751f\u6d3b\u65b9\u5f0f",
        "questionType": "\u4e8c\u9009\u4e00",
        "questionType2": "Q2 \u8bdd\u9898\u5206\u7c7b",
        "userCount": 0,
        "tagCount": 0,
        "recordCount": 0
    },
    {
        "_id": "62382eae051b20466f377c8f",
        "title": "Official 57 Q3",
        "TPO": 57,
        "questionNumber": 3,
        "tag": "\u6559\u5b66\u5b89\u6392",
        "questionType": "\u7efc\u5408",
        "questionType2": "Q3 \u6821\u56ed\u573a\u666f",
        "userCount": 0,
        "tagCount": 0,
        "recordCount": 0
    },
    {
        "_id": "623830d5051b20466f37b176",
        "title": "Official 57 Q4",
        "TPO": 57,
        "questionNumber": 4,
        "tag": "\u751f\u7269",
        "questionType": "\u7efc\u5408",
        "questionType2": "Q4&Q6 \u5b66\u672f\u7c7b\u8bb2\u5ea7",
        "userCount": 0,
        "tagCount": 0,
        "recordCount": 0
    },
    {
        "_id": "62383210051b20466f37c3ee",
        "title": "Official 57 Q6",
        "TPO": 57,
        "questionNumber": 6,
        "tag": "\u5546\u4e1a",
        "questionType": "\u7efc\u5408",
        "questionType2": "Q4&Q6 \u5b66\u672f\u7c7b\u8bb2\u5ea7",
        "userCount": 0,
        "tagCount": 0,
        "recordCount": 0
    },
    {
        "_id": "62383544051b20466f37fd0a",
        "title": "Official 58 Q2",
        "TPO": 58,
        "questionNumber": 2,
        "tag": "\u751f\u6d3b\u65b9\u5f0f",
        "questionType": "\u4e8c\u9009\u4e00",
        "questionType2": "Q2 \u8bdd\u9898\u5206\u7c7b",
        "userCount": 0,
        "tagCount": 0,
        "recordCount": 0
    },
    {
        "_id": "623836cd051b20466f382953",
        "title": "Official 58 Q3",
        "TPO": 58,
        "questionNumber": 3,
        "tag": "\u540e\u52e4\u670d\u52a1",
        "questionType": "\u7efc\u5408",
        "questionType2": "Q3 \u6821\u56ed\u573a\u666f",
        "userCount": 0,
        "tagCount": 0,
        "recordCount": 0
    },
    {
        "_id": "62383834051b20466f385814",
        "title": "Official 58 Q4",
        "TPO": 58,
        "questionNumber": 4,
        "tag": "\u751f\u7269",
        "questionType": "\u7efc\u5408",
        "questionType2": "Q4&Q6 \u5b66\u672f\u7c7b\u8bb2\u5ea7",
        "userCount": 0,
        "tagCount": 0,
        "recordCount": 0
    },
    {
        "_id": "6238396c051b20466f3872d7",
        "title": "Official 58 Q6",
        "TPO": 58,
        "questionNumber": 6,
        "tag": "\u5546\u4e1a",
        "questionType": "\u7efc\u5408",
        "questionType2": "Q4&Q6 \u5b66\u672f\u7c7b\u8bb2\u5ea7",
        "userCount": 0,
        "tagCount": 0,
        "recordCount": 0
    },
    {
        "_id": "6242c24889515d1bb23e6063",
        "title": "Official 59 Q2",
        "TPO": 59,
        "questionNumber": 2,
        "tag": "\u6559\u80b2\u5de5\u4f5c",
        "questionType": "Agree or Disagree",
        "questionType2": "Q2 \u8bdd\u9898\u5206\u7c7b",
        "userCount": 0,
        "tagCount": 0,
        "recordCount": 0
    },
    {
        "_id": "6242c32d89515d1bb23e6b68",
        "title": "Official 59 Q3",
        "TPO": 59,
        "questionNumber": 3,
        "tag": "\u8bfe\u7a0b\u5b89\u6392",
        "questionType": "\u7efc\u5408",
        "questionType2": "Q3 \u6821\u56ed\u573a\u666f",
        "userCount": 0,
        "tagCount": 0,
        "recordCount": 0
    },
    {
        "_id": "6242c41289515d1bb23e798c",
        "title": "Official 59 Q4",
        "TPO": 59,
        "questionNumber": 4,
        "tag": "\u793e\u4f1a\u5b66",
        "questionType": "\u7efc\u5408",
        "questionType2": "Q4&Q6 \u5b66\u672f\u7c7b\u8bb2\u5ea7",
        "userCount": 0,
        "tagCount": 0,
        "recordCount": 0
    },
    {
        "_id": "6242c493078470fa88ebfc69",
        "title": "Official 59 Q6",
        "TPO": 59,
        "questionNumber": 6,
        "tag": "\u751f\u7269",
        "questionType": "\u7efc\u5408",
        "questionType2": "Q4&Q6 \u5b66\u672f\u7c7b\u8bb2\u5ea7",
        "userCount": 0,
        "tagCount": 0,
        "recordCount": 0
    },
    {
        "_id": "62383ebc051b20466f389793",
        "title": "Official 60 Q2",
        "TPO": 60,
        "questionNumber": 2,
        "tag": "\u6559\u80b2\u5de5\u4f5c",
        "questionType": "Agree or Disagree",
        "questionType2": "Q2 \u8bdd\u9898\u5206\u7c7b",
        "userCount": 0,
        "tagCount": 0,
        "recordCount": 0
    },
    {
        "_id": "623840ff051b20466f38a4e4",
        "title": "Official 60 Q3",
        "TPO": 60,
        "questionNumber": 3,
        "tag": "\u540e\u52e4\u670d\u52a1",
        "questionType": "\u7efc\u5408",
        "questionType2": "Q3 \u6821\u56ed\u573a\u666f",
        "userCount": 0,
        "tagCount": 0,
        "recordCount": 0
    },
    {
        "_id": "623841ff051b20466f38a943",
        "title": "Official 60 Q4",
        "TPO": 60,
        "questionNumber": 4,
        "tag": "\u751f\u7269",
        "questionType": "\u7efc\u5408",
        "questionType2": "Q4&Q6 \u5b66\u672f\u7c7b\u8bb2\u5ea7",
        "userCount": 0,
        "tagCount": 0,
        "recordCount": 0
    },
    {
        "_id": "6238429e051b20466f38aa9f",
        "title": "Official 60 Q6",
        "TPO": 60,
        "questionNumber": 6,
        "tag": "\u5546\u4e1a",
        "questionType": "\u7efc\u5408",
        "questionType2": "Q4&Q6 \u5b66\u672f\u7c7b\u8bb2\u5ea7",
        "userCount": 0,
        "tagCount": 0,
        "recordCount": 0
    },
    {
        "_id": "6238454d051b20466f38b050",
        "title": "Official 61 Q2",
        "TPO": 61,
        "questionNumber": 2,
        "tag": "\u6559\u80b2\u5de5\u4f5c",
        "questionType": "\u4e8c\u9009\u4e00",
        "questionType2": "Q2 \u8bdd\u9898\u5206\u7c7b",
        "userCount": 0,
        "tagCount": 0,
        "recordCount": 0
    },
    {
        "_id": "6238461f051b20466f38b703",
        "title": "Official 61 Q3",
        "TPO": 61,
        "questionNumber": 3,
        "tag": "\u6559\u5b66\u5b89\u6392",
        "questionType": "\u7efc\u5408",
        "questionType2": "Q3 \u6821\u56ed\u573a\u666f",
        "userCount": 0,
        "tagCount": 0,
        "recordCount": 0
    },
    {
        "_id": "623846ae051b20466f38b9f2",
        "title": "Official 61 Q4",
        "TPO": 61,
        "questionNumber": 4,
        "tag": "\u793e\u4f1a\u5b66",
        "questionType": "\u7efc\u5408",
        "questionType2": "Q4&Q6 \u5b66\u672f\u7c7b\u8bb2\u5ea7",
        "userCount": 0,
        "tagCount": 0,
        "recordCount": 0
    },
    {
        "_id": "62384729051b20466f38bef3",
        "title": "Official 61 Q6",
        "TPO": 61,
        "questionNumber": 6,
        "tag": "\u751f\u7269",
        "questionType": "\u7efc\u5408",
        "questionType2": "Q4&Q6 \u5b66\u672f\u7c7b\u8bb2\u5ea7",
        "userCount": 0,
        "tagCount": 0,
        "recordCount": 0
    },
    {
        "_id": "62384861051b20466f38c4ad",
        "title": "Official 62 Q2",
        "TPO": 62,
        "questionNumber": 2,
        "tag": "\u6559\u80b2\u5de5\u4f5c",
        "questionType": "Agree or Disagree",
        "questionType2": "Q2 \u8bdd\u9898\u5206\u7c7b",
        "userCount": 0,
        "tagCount": 0,
        "recordCount": 0
    },
    {
        "_id": "62384918051b20466f38c750",
        "title": "Official 62 Q3",
        "TPO": 62,
        "questionNumber": 3,
        "tag": "\u57fa\u7840\u5efa\u8bbe",
        "questionType": "\u7efc\u5408",
        "questionType2": "Q3 \u6821\u56ed\u573a\u666f",
        "userCount": 0,
        "tagCount": 0,
        "recordCount": 0
    },
    {
        "_id": "62384a3f051b20466f38cba7",
        "title": "Official 62 Q4",
        "TPO": 62,
        "questionNumber": 4,
        "tag": "\u5fc3\u7406",
        "questionType": "\u7efc\u5408",
        "questionType2": "Q4&Q6 \u5b66\u672f\u7c7b\u8bb2\u5ea7",
        "userCount": 0,
        "tagCount": 0,
        "recordCount": 0
    },
    {
        "_id": "62384aab051b20466f38d0a1",
        "title": "Official 62 Q6",
        "TPO": 62,
        "questionNumber": 6,
        "tag": "\u751f\u7269",
        "questionType": "\u7efc\u5408",
        "questionType2": "Q4&Q6 \u5b66\u672f\u7c7b\u8bb2\u5ea7",
        "userCount": 0,
        "tagCount": 0,
        "recordCount": 0
    },
    {
        "_id": "62384baa051b20466f38d12d",
        "title": "Official 63 Q2",
        "TPO": 63,
        "questionNumber": 2,
        "tag": "\u6559\u80b2\u5de5\u4f5c",
        "questionType": "Agree or Disagree",
        "questionType2": "Q2 \u8bdd\u9898\u5206\u7c7b",
        "userCount": 0,
        "tagCount": 0,
        "recordCount": 0
    },
    {
        "_id": "62384c84051b20466f38d6ed",
        "title": "Official 63 Q3",
        "TPO": 63,
        "questionNumber": 3,
        "tag": "\u8bfe\u7a0b\u5b89\u6392",
        "questionType": "\u7efc\u5408",
        "questionType2": "Q3 \u6821\u56ed\u573a\u666f",
        "userCount": 0,
        "tagCount": 0,
        "recordCount": 0
    },
    {
        "_id": "62384d0a051b20466f38dc9c",
        "title": "Official 63 Q4",
        "TPO": 63,
        "questionNumber": 4,
        "tag": "\u751f\u7269",
        "questionType": "\u7efc\u5408",
        "questionType2": "Q4&Q6 \u5b66\u672f\u7c7b\u8bb2\u5ea7",
        "userCount": 0,
        "tagCount": 0,
        "recordCount": 0
    },
    {
        "_id": "62384de6051b20466f38e095",
        "title": "Official 63 Q6",
        "TPO": 63,
        "questionNumber": 6,
        "tag": "\u5546\u4e1a",
        "questionType": "\u7efc\u5408",
        "questionType2": "Q4&Q6 \u5b66\u672f\u7c7b\u8bb2\u5ea7",
        "userCount": 0,
        "tagCount": 0,
        "recordCount": 0
    },
    {
        "_id": "62384eb2051b20466f38e93e",
        "title": "Official 64 Q2",
        "TPO": 64,
        "questionNumber": 2,
        "tag": "\u6559\u80b2\u5de5\u4f5c",
        "questionType": "\u4e8c\u9009\u4e00",
        "questionType2": "Q2 \u8bdd\u9898\u5206\u7c7b",
        "userCount": 0,
        "tagCount": 0,
        "recordCount": 0
    },
    {
        "_id": "62384f6d051b20466f38f2b5",
        "title": "Official 64 Q3",
        "TPO": 64,
        "questionNumber": 3,
        "tag": "\u57fa\u7840\u5efa\u8bbe",
        "questionType": "\u7efc\u5408",
        "questionType2": "Q3 \u6821\u56ed\u573a\u666f",
        "userCount": 0,
        "tagCount": 0,
        "recordCount": 0
    },
    {
        "_id": "6238501e051b20466f38f660",
        "title": "Official 64 Q4",
        "TPO": 64,
        "questionNumber": 4,
        "tag": "\u5fc3\u7406",
        "questionType": "\u7efc\u5408",
        "questionType2": "Q4&Q6 \u5b66\u672f\u7c7b\u8bb2\u5ea7",
        "userCount": 0,
        "tagCount": 0,
        "recordCount": 0
    },
    {
        "_id": "62385087051b20466f38fa3c",
        "title": "Official 64 Q6",
        "TPO": 64,
        "questionNumber": 6,
        "tag": "\u73af\u5883",
        "questionType": "\u7efc\u5408",
        "questionType2": "Q4&Q6 \u5b66\u672f\u7c7b\u8bb2\u5ea7",
        "userCount": 0,
        "tagCount": 0,
        "recordCount": 0
    },
    {
        "_id": "62385146051b20466f3901c4",
        "title": "Official 65 Q2",
        "TPO": 65,
        "questionNumber": 2,
        "tag": "\u793e\u4f1a\u8bdd\u9898",
        "questionType": "Agree or Disagree",
        "questionType2": "Q2 \u8bdd\u9898\u5206\u7c7b",
        "userCount": 0,
        "tagCount": 0,
        "recordCount": 0
    },
    {
        "_id": "623851fc051b20466f39088a",
        "title": "Official 65 Q3",
        "TPO": 65,
        "questionNumber": 3,
        "tag": "\u540e\u52e4\u670d\u52a1",
        "questionType": "\u7efc\u5408",
        "questionType2": "Q3 \u6821\u56ed\u573a\u666f",
        "userCount": 0,
        "tagCount": 0,
        "recordCount": 0
    },
    {
        "_id": "6238529a051b20466f390b2b",
        "title": "Official 65 Q4",
        "TPO": 65,
        "questionNumber": 4,
        "tag": "\u5fc3\u7406",
        "questionType": "\u7efc\u5408",
        "questionType2": "Q4&Q6 \u5b66\u672f\u7c7b\u8bb2\u5ea7",
        "userCount": 0,
        "tagCount": 0,
        "recordCount": 0
    },
    {
        "_id": "623852ed051b20466f390ce6",
        "title": "Official 65 Q6",
        "TPO": 65,
        "questionNumber": 6,
        "tag": "\u751f\u7269",
        "questionType": "\u7efc\u5408",
        "questionType2": "Q4&Q6 \u5b66\u672f\u7c7b\u8bb2\u5ea7",
        "userCount": 0,
        "tagCount": 0,
        "recordCount": 0
    }
]
